Workbook

Sheet Cover
A1: CSL Limited — cross-scenario valuation (v2: terminal capex=D&A)
A2: Six-scenario distribution • USD functional, AUD at spot • 25 June 2026 • Reid Advisory
A4: Scenario | B4: Per share USD | C4: Per share AUD | D4: vs Market | E4: vs Muddle Through | F4: Terminal % EV
A5: Orderly Convergence | B5: ='S_Orderly'!C42 | C5: ='S_Orderly'!C43 | D5: ='S_Orderly'!C43/Inputs!$B$22-1 | E5: ='S_Orderly'!C42/'S_Muddle'!C42-1 | F5: ='S_Orderly'!C44
A6: Muddle Through | B6: ='S_Muddle'!C42 | C6: ='S_Muddle'!C43 | D6: ='S_Muddle'!C43/Inputs!$B$22-1 | E6: ='S_Muddle'!C42/'S_Muddle'!C42-1 | F6: ='S_Muddle'!C44
A7: AI Productivity Lag | B7: ='S_AI'!C42 | C7: ='S_AI'!C43 | D7: ='S_AI'!C43/Inputs!$B$22-1 | E7: ='S_AI'!C42/'S_Muddle'!C42-1 | F7: ='S_AI'!C44
A8: Disorderly Climate | B8: ='S_Disorderly'!C42 | C8: ='S_Disorderly'!C43 | D8: ='S_Disorderly'!C43/Inputs!$B$22-1 | E8: ='S_Disorderly'!C42/'S_Muddle'!C42-1 | F8: ='S_Disorderly'!C44
A9: Fragmentation | B9: ='S_Fragmentation'!C42 | C9: ='S_Fragmentation'!C43 | D9: ='S_Fragmentation'!C43/Inputs!$B$22-1 | E9: ='S_Fragmentation'!C42/'S_Muddle'!C42-1 | F9: ='S_Fragmentation'!C44
A10: Stagflation Persists | B10: ='S_Stagflation'!C42 | C10: ='S_Stagflation'!C43 | D10: ='S_Stagflation'!C43/Inputs!$B$22-1 | E10: ='S_Stagflation'!C42/'S_Muddle'!C42-1 | F10: ='S_Stagflation'!C44
A12: Upside (Orderly − MT), USD | B12: ='S_Orderly'!C42-'S_Muddle'!C42
A13: Downside (MT − Stagflation), USD | B13: ='S_Muddle'!C42-'S_Stagflation'!C42
A14: Asymmetry ratio (down/up) | B14: =B13/B12
A16: Observation 1 — Defensive shape. Asymmetry ~1.3x: downside modestly exceeds upside, far below DNL's cyclical 4.05x and below WBC's 1.83x. Plasma demand is volume-inelastic, so scenarios transmit through margins (donor-collection wages, energy/carbon cost, payor pricing) and policy, not volumes.
A17: Observation 2 — Whole distribution above market. Even Stagflation (~AUD 160) sits well above market (AUD 105.53); Muddle Through is +93%. Per §16 the market is implicitly pricing a state more bearish than the framework's downside boundary. The §3.5.7 tab shows no single plausible lever reconciles to market — it requires a blend of pessimism (or genuine under-pricing).
A18: Observation 3 — Terminal-heavy. Terminal value ~74–77% of EV (long-duration compounder at ~30% terminal margin, 3% g, 8.75% Re). v2 fix: terminal capex set = D&A (steady-state), removing the perpetual D&A>capex cash inflation that lifted v1 ~5%.
A19: Single discount rate 8.75% (Rf 4.5% + β0.85 × ERP 5.0%) held across all scenarios per the single-WACC discipline; scenario risk is priced in the cash-flow paths, not the rate. β0.85 remains an open sanity-check (a stressed β1.2 → Re10.5% cuts MT ~26%).

Sheet Market-Implied (§3.5.7)
A1: Market-implied cross-check (§3.5.7) — what must the price believe?
A3: Market price (AUD) | B3: =Inputs!B22
A4: Market price (USD/sh) | B4: =B3/Inputs!B21
A5: Implied market equity (USD m) | B5: =B4*Inputs!B20
A6: Add net debt + restructuring → EV target (USD m) | B6: =B5+Inputs!B18+Inputs!B19
A8: Framework MT explicit PV (FY27–31, USD m) | B8: ='S_Muddle'!C32
A9: → Required terminal PV to hit market (USD m) | B9: =B6-B8
A10: Framework MT terminal PV (USD m) | B10: ='S_Muddle'!C36
A11: Market needs terminal PV as % of framework's | B11: =B9/B10
A13: Required terminal value (USD m) = reqTermPV ÷ df5 | B13: =B9/'S_Muddle'!C35
A14: Required terminal FCFF = reqTV × (Re − g) | B14: =B13*(Inputs!B23-Inputs!D38)
A15: IMPLIED terminal EBIT margin (live formula) | B15: =(B14/(1+Inputs!D38)-'S_Muddle'!H17*(Inputs!B12-Inputs!B13-Inputs!D38*Inputs!B14))/('S_Muddle'!H17*(1-Inputs!D39))
A16: vs framework terminal margin | B16: =Inputs!D37
A18: Single-lever market-implied values (goal-seek; all else at MT):
A19: Implied cost of equity Re [goal-seek] | B19: 0.1305 | C19: ⇒ beta ≈ 1.71 (we use 8.75% / beta 0.85)
A20: Implied terminal EBIT margin [goal-seek] | B20: 0.135 | C20: (we use 30.0%; FY25 actual 27.5%)
A21: Implied terminal growth g [goal-seek] | B21: -0.041 | C21: (we use 3.0%; implies perpetual contraction)
A23: Read-through
A24: No single lever at a plausible value reconciles to the market price: it needs β≈1.7–1.8, OR a terminal margin near half the FY25 level, OR perpetual contraction. The price is therefore a blend of pessimism across discount rate, margin and growth — or the franchise is genuinely under-priced.
A25: The live implied-margin formula (B15) and the goal-seek Re/g are documented outputs, not model inputs — they read the market, they don't drive the DCF.
A26: Disciplined next step: decide which framework inputs to move on their own merits (β / cost of equity is the strongest candidate), rather than re-tuning to match the market (§16: gaps are informative, not errors).

Sheet Inputs
A1: CSL scenarios — shared base + per-scenario drivers
A2: Shared base (identical across scenarios)
A3: Behring revenue FY25 (USD m) | B3: 11158
A4: Seqirus revenue FY25 (USD m) | B4: 2166
A5: Vifor revenue FY25 (USD m) | B5: 2234
A6: Group revenue FY25 (USD m) | B6: 15558
A7: Behring OR margin FY25 | B7: 0.422
A8: Seqirus OR margin FY25 | B8: 0.474
A9: Vifor OR margin FY25 | B9: 0.491
A10: Corporate/unalloc FY25 (USD m) | B10: -2559
A11: Capex / revenue | B11: 0.045
A12: D&A / revenue | B12: 0.06
A13: Terminal capex / revenue (=D&A, steady state) | B13: 0.06
A14: Working-capital change / Δrevenue | B14: 0.1
... A22: Market price (AUD) | B22: 105.53
A23: Cost of equity Re = Rf + beta x ERP (derived) | B23: =B15+B17*B16
A25: Driver | C25: Orderly Convergence | D25: Muddle Through | E25: AI Productivity Lag | F25: Disorderly Climate | G25: Fragmentation | H25: Stagflation Persists
A26: Behring growth FY26 | C26: -0.005 | D26: -0.01 | E26: -0.01 | F26: -0.01 | G26: -0.015 | H26: -0.015
A27: Behring growth FY27 | C27: 0.04 | D27: 0.025 | E27: 0.025 | F27: 0.02 | G27: 0.015 | H27: 0.01
A28: Behring growth FY28 | C28: 0.055 | D28: 0.045 | E28: 0.045 | F28: 0.035 | G28: 0.03 | H28: 0.025
A29: Behring growth FY29 | C29: 0.065 | D29: 0.055 | E29: 0.05 | F29: 0.045 | G29: 0.04 | H29: 0.035
A30: Behring growth FY30 | C30: 0.065 | D30: 0.055 | E30: 0.05 | F30: 0.045 | G30: 0.04 | H30: 0.035
A31: Behring growth FY31 | C31: 0.065 | D31: 0.055 | E31: 0.05 | F31: 0.045 | G31: 0.04 | H31: 0.035
A32: Seqirus revenue CAGR | C32: 0.025 | D32: 0.02 | E32: 0.02 | F32: 0.03 | G32: 0.015 | H32: 0.01
A33: Vifor revenue CAGR | C33: 0.085 | D33: 0.07 | E33: 0.065 | F33: 0.05 | G33: 0.055 | H33: 0.04
A34: Behring margin uplift (cum, FY31) | C34: 0.025 | D34: 0.015 | E34: 0.0175 | F34: -0.005 | G34: 0 | H34: -0.015
A35: Seqirus margin uplift (cum, FY31) | C35: 0.015 | D35: 0.01 | E35: 0.01 | F35: 0.005 | G35: 0 | H35: -0.005
A36: Vifor margin uplift (cum, FY31) | C36: 0.015 | D36: 0.01 | E36: 0.01 | F36: 0 | G36: 0 | H36: -0.005
A37: Terminal EBIT margin | C37: 0.315 | D37: 0.3 | E37: 0.3025 | F37: 0.28 | G37: 0.282 | H37: 0.265
... A39: Effective tax rate | C39: 0.19 | D39: 0.19 | E39: 0.19 | F39: 0.19 | G39: 0.2 | H39: 0.19

Sheet S_Orderly
A1: Orderly Convergence — segment DCF (USD m)
A3: Line | B3: FY25 | C3: FY26 | D3: FY27 | E3: FY28 | F3: FY29 | G3: FY30 | H3: FY31
A5: Behring revenue | B5: =Inputs!$B$3 | C5: =B5*(1+Inputs!$C$26) | D5: =C5*(1+Inputs!$C$27) | E5: =D5*(1+Inputs!$C$28) | F5: =E5*(1+Inputs!$C$29) | G5: =F5*(1+Inputs!$C$30) | H5: =G5*(1+Inputs!$C$31)
A6: Behring OR margin | B6: =Inputs!$B$7 | C6: =Inputs!$B$7+Inputs!$C$34*(1/6) | D6: =Inputs!$B$7+Inputs!$C$34*(2/6) | E6: =Inputs!$B$7+Inputs!$C$34*(3/6) | F6: =Inputs!$B$7+Inputs!$C$34*(4/6) | G6: =Inputs!$B$7+Inputs!$C$34*(5/6) | H6: =Inputs!$B$7+Inputs!$C$34*(6/6)
A7: Behring OR | B7: =B5*B6 | C7: =C5*C6 | D7: =D5*D6 | E7: =E5*E6 | F7: =F5*F6 | G7: =G5*G6 | H7: =H5*H6
A9: Seqirus revenue | B9: =Inputs!$B$4 | C9: =B9*(1+Inputs!$C$32) | D9: =C9*(1+Inputs!$C$32) | E9: =D9*(1+Inputs!$C$32) | F9: =E9*(1+Inputs!$C$32) | G9: =F9*(1+Inputs!$C$32) | H9: =G9*(1+Inputs!$C$32)
A10: Seqirus OR margin | B10: =Inputs!$B$8 | C10: =Inputs!$B$8+Inputs!$C$35*(1/6) | D10: =Inputs!$B$8+Inputs!$C$35*(2/6) | E10: =Inputs!$B$8+Inputs!$C$35*(3/6) | F10: =Inputs!$B$8+Inputs!$C$35*(4/6) | G10: =Inputs!$B$8+Inputs!$C$35*(5/6) | H10: =Inputs!$B$8+Inputs!$C$35*(6/6)
A11: Seqirus OR | B11: =B9*B10 | C11: =C9*C10 | D11: =D9*D10 | E11: =E9*E10 | F11: =F9*F10 | G11: =G9*G10 | H11: =H9*H10
A13: Vifor revenue | B13: =Inputs!$B$5 | C13: =B13*(1+Inputs!$C$33) | D13: =C13*(1+Inputs!$C$33) | E13: =D13*(1+Inputs!$C$33) | F13: =E13*(1+Inputs!$C$33) | G13: =F13*(1+Inputs!$C$33) | H13: =G13*(1+Inputs!$C$33)
A14: Vifor OR margin | B14: =Inputs!$B$9 | C14: =Inputs!$B$9+Inputs!$C$36*(1/6) | D14: =Inputs!$B$9+Inputs!$C$36*(2/6) | E14: =Inputs!$B$9+Inputs!$C$36*(3/6) | F14: =Inputs!$B$9+Inputs!$C$36*(4/6) | G14: =Inputs!$B$9+Inputs!$C$36*(5/6) | H14: =Inputs!$B$9+Inputs!$C$36*(6/6)
A15: Vifor OR | B15: =B13*B14 | C15: =C13*C14 | D15: =D13*D14 | E15: =E13*E14 | F15: =F13*F14 | G15: =G13*G14 | H15: =H13*H14
A17: Group revenue | B17: =B5+B9+B13 | C17: =C5+C9+C13 | D17: =D5+D9+D13 | E17: =E5+E9+E13 | F17: =F5+F9+F13 | G17: =G5+G9+G13 | H17: =H5+H9+H13
A18: Segment OR (sum) | B18: =B7+B11+B15 | C18: =C7+C11+C15 | D18: =D7+D11+D15 | E18: =E7+E11+E15 | F18: =F7+F11+F15 | G18: =G7+G11+G15 | H18: =H7+H11+H15
A19: Corporate / unalloc | B19: =Inputs!$B$10 | C19: =Inputs!$B$10*(1.005^1) | D19: =Inputs!$B$10*(1.005^2) | E19: =Inputs!$B$10*(1.005^3) | F19: =Inputs!$B$10*(1.005^4) | G19: =Inputs!$B$10*(1.005^5) | H19: =Inputs!$B$10*(1.005^6)
A20: Group EBIT | B20: =B18+B19 | C20: =C18+C19 | D20: =D18+D19 | E20: =E18+E19 | F20: =F18+F19 | G20: =G18+G19 | H20: =H18+H19
A21: Group EBIT margin (memo) | B21: =B20/B17 | C21: =C20/C17 | D21: =D20/D17 | E21: =E20/E17 | F21: =F20/F17 | G21: =G20/G17 | H21: =H20/H17
A23: NOPAT = EBIT x (1-tax) | C23: =C20*(1-Inputs!$C$39) | D23: =D20*(1-Inputs!$C$39) | E23: =E20*(1-Inputs!$C$39) | F23: =F20*(1-Inputs!$C$39) | G23: =G20*(1-Inputs!$C$39) | H23: =H20*(1-Inputs!$C$39)
A24: Plus: D&A | C24: =C17*Inputs!$B$12 | D24: =D17*Inputs!$B$12 | E24: =E17*Inputs!$B$12 | F24: =F17*Inputs!$B$12 | G24: =G17*Inputs!$B$12 | H24: =H17*Inputs!$B$12
A25: Less: capex (explicit yrs) | C25: =-C17*Inputs!$B$11 | D25: =-D17*Inputs!$B$11 | E25: =-E17*Inputs!$B$11 | F25: =-F17*Inputs!$B$11 | G25: =-G17*Inputs!$B$11 | H25: =-H17*Inputs!$B$11
A26: Less: WC change | C26: =-(C17-B17)*Inputs!$B$14 | D26: =-(D17-C17)*Inputs!$B$14 | E26: =-(E17-D17)*Inputs!$B$14 | F26: =-(F17-E17)*Inputs!$B$14 | G26: =-(G17-F17)*Inputs!$B$14 | H26: =-(H17-G17)*Inputs!$B$14
A27: FCFF | C27: =C23+C24+C25+C26 | D27: =D23+D24+D25+D26 | E27: =E23+E24+E25+E26 | F27: =F23+F24+F25+F26 | G27: =G23+G24+G25+G26 | H27: =H23+H24+H25+H26
A28: Mid-period t (FY26 excl.) | C28: 0 | D28: 0.5 | E28: 1.5 | F28: 2.5 | G28: 3.5 | H28: 4.5
A29: Discount factor | C29: =1/(1+Inputs!$B$23)^C28 | D29: =1/(1+Inputs!$B$23)^D28 | E29: =1/(1+Inputs!$B$23)^E28 | F29: =1/(1+Inputs!$B$23)^F28 | G29: =1/(1+Inputs!$B$23)^G28 | H29: =1/(1+Inputs!$B$23)^H28
A30: PV of FCFF (FY27–FY31) | C30: 0 | D30: =D27*D29 | E30: =E27*E29 | F30: =F27*F29 | G30: =G27*G29 | H30: =H27*H29
A32: Sum explicit PV (FY27–FY31) | C32: =SUM(D30:H30)
A33: Terminal FCFF (FY31; capex=D&A) | C33: =(H17*Inputs!$C$37*(1-Inputs!$C$39)+H17*Inputs!$B$12-H17*Inputs!$B$13-H17*Inputs!$C$38*Inputs!$B$14)*(1+Inputs!$C$38)
A34: Terminal value (Gordon) | C34: =C33/(Inputs!$B$23-Inputs!$C$38)
A35: Discount factor t=5 | C35: =1/(1+Inputs!$B$23)^5
A36: PV of terminal value | C36: =C34*C35
A37: Enterprise value | C37: =C32+C36
A38: Less: net debt | C38: =-Inputs!$B$18
A39: Less: restructuring cash | C39: =-Inputs!$B$19
A40: Equity value | C40: =C37+C38+C39
A41: Shares (m) | C41: =Inputs!$B$20
A42: Value per share (USD) | C42: =C40/C41
A43: Value per share (AUD) | C43: =C42*Inputs!$B$21
A44: Terminal % of EV (memo) | C44: =C36/C37

Sheet S_Muddle
A1: Muddle Through — segment DCF (USD m)
A3: Line | B3: FY25 | C3: FY26 | D3: FY27 | E3: FY28 | F3: FY29 | G3: FY30 | H3: FY31
A5: Behring revenue | B5: =Inputs!$B$3 | C5: =B5*(1+Inputs!$D$26) | D5: =C5*(1+Inputs!$D$27) | E5: =D5*(1+Inputs!$D$28) | F5: =E5*(1+Inputs!$D$29) | G5: =F5*(1+Inputs!$D$30) | H5: =G5*(1+Inputs!$D$31)
A6: Behring OR margin | B6: =Inputs!$B$7 | C6: =Inputs!$B$7+Inputs!$D$34*(1/6) | D6: =Inputs!$B$7+Inputs!$D$34*(2/6) | E6: =Inputs!$B$7+Inputs!$D$34*(3/6) | F6: =Inputs!$B$7+Inputs!$D$34*(4/6) | G6: =Inputs!$B$7+Inputs!$D$34*(5/6) | H6: =Inputs!$B$7+Inputs!$D$34*(6/6)
A7: Behring OR | B7: =B5*B6 | C7: =C5*C6 | D7: =D5*D6 | E7: =E5*E6 | F7: =F5*F6 | G7: =G5*G6 | H7: =H5*H6
A9: Seqirus revenue | B9: =Inputs!$B$4 | C9: =B9*(1+Inputs!$D$32) | D9: =C9*(1+Inputs!$D$32) | E9: =D9*(1+Inputs!$D$32) | F9: =E9*(1+Inputs!$D$32) | G9: =F9*(1+Inputs!$D$32) | H9: =G9*(1+Inputs!$D$32)
A10: Seqirus OR margin | B10: =Inputs!$B$8 | C10: =Inputs!$B$8+Inputs!$D$35*(1/6) | D10: =Inputs!$B$8+Inputs!$D$35*(2/6) | E10: =Inputs!$B$8+Inputs!$D$35*(3/6) | F10: =Inputs!$B$8+Inputs!$D$35*(4/6) | G10: =Inputs!$B$8+Inputs!$D$35*(5/6) | H10: =Inputs!$B$8+Inputs!$D$35*(6/6)
A11: Seqirus OR | B11: =B9*B10 | C11: =C9*C10 | D11: =D9*D10 | E11: =E9*E10 | F11: =F9*F10 | G11: =G9*G10 | H11: =H9*H10
A13: Vifor revenue | B13: =Inputs!$B$5 | C13: =B13*(1+Inputs!$D$33) | D13: =C13*(1+Inputs!$D$33) | E13: =D13*(1+Inputs!$D$33) | F13: =E13*(1+Inputs!$D$33) | G13: =F13*(1+Inputs!$D$33) | H13: =G13*(1+Inputs!$D$33)
A14: Vifor OR margin | B14: =Inputs!$B$9 | C14: =Inputs!$B$9+Inputs!$D$36*(1/6) | D14: =Inputs!$B$9+Inputs!$D$36*(2/6) | E14: =Inputs!$B$9+Inputs!$D$36*(3/6) | F14: =Inputs!$B$9+Inputs!$D$36*(4/6) | G14: =Inputs!$B$9+Inputs!$D$36*(5/6) | H14: =Inputs!$B$9+Inputs!$D$36*(6/6)
A15: Vifor OR | B15: =B13*B14 | C15: =C13*C14 | D15: =D13*D14 | E15: =E13*E14 | F15: =F13*F14 | G15: =G13*G14 | H15: =H13*H14
A17: Group revenue | B17: =B5+B9+B13 | C17: =C5+C9+C13 | D17: =D5+D9+D13 | E17: =E5+E9+E13 | F17: =F5+F9+F13 | G17: =G5+G9+G13 | H17: =H5+H9+H13
A18: Segment OR (sum) | B18: =B7+B11+B15 | C18: =C7+C11+C15 | D18: =D7+D11+D15 | E18: =E7+E11+E15 | F18: =F7+F11+F15 | G18: =G7+G11+G15 | H18: =H7+H11+H15
A19: Corporate / unalloc | B19: =Inputs!$B$10 | C19: =Inputs!$B$10*(1.005^1) | D19: =Inputs!$B$10*(1.005^2) | E19: =Inputs!$B$10*(1.005^3) | F19: =Inputs!$B$10*(1.005^4) | G19: =Inputs!$B$10*(1.005^5) | H19: =Inputs!$B$10*(1.005^6)
A20: Group EBIT | B20: =B18+B19 | C20: =C18+C19 | D20: =D18+D19 | E20: =E18+E19 | F20: =F18+F19 | G20: =G18+G19 | H20: =H18+H19
A21: Group EBIT margin (memo) | B21: =B20/B17 | C21: =C20/C17 | D21: =D20/D17 | E21: =E20/E17 | F21: =F20/F17 | G21: =G20/G17 | H21: =H20/H17
A23: NOPAT = EBIT x (1-tax) | C23: =C20*(1-Inputs!$D$39) | D23: =D20*(1-Inputs!$D$39) | E23: =E20*(1-Inputs!$D$39) | F23: =F20*(1-Inputs!$D$39) | G23: =G20*(1-Inputs!$D$39) | H23: =H20*(1-Inputs!$D$39)
A24: Plus: D&A | C24: =C17*Inputs!$B$12 | D24: =D17*Inputs!$B$12 | E24: =E17*Inputs!$B$12 | F24: =F17*Inputs!$B$12 | G24: =G17*Inputs!$B$12 | H24: =H17*Inputs!$B$12
A25: Less: capex (explicit yrs) | C25: =-C17*Inputs!$B$11 | D25: =-D17*Inputs!$B$11 | E25: =-E17*Inputs!$B$11 | F25: =-F17*Inputs!$B$11 | G25: =-G17*Inputs!$B$11 | H25: =-H17*Inputs!$B$11
A26: Less: WC change | C26: =-(C17-B17)*Inputs!$B$14 | D26: =-(D17-C17)*Inputs!$B$14 | E26: =-(E17-D17)*Inputs!$B$14 | F26: =-(F17-E17)*Inputs!$B$14 | G26: =-(G17-F17)*Inputs!$B$14 | H26: =-(H17-G17)*Inputs!$B$14
A27: FCFF | C27: =C23+C24+C25+C26 | D27: =D23+D24+D25+D26 | E27: =E23+E24+E25+E26 | F27: =F23+F24+F25+F26 | G27: =G23+G24+G25+G26 | H27: =H23+H24+H25+H26
A28: Mid-period t (FY26 excl.) | C28: 0 | D28: 0.5 | E28: 1.5 | F28: 2.5 | G28: 3.5 | H28: 4.5
A29: Discount factor | C29: =1/(1+Inputs!$B$23)^C28 | D29: =1/(1+Inputs!$B$23)^D28 | E29: =1/(1+Inputs!$B$23)^E28 | F29: =1/(1+Inputs!$B$23)^F28 | G29: =1/(1+Inputs!$B$23)^G28 | H29: =1/(1+Inputs!$B$23)^H28
A30: PV of FCFF (FY27–FY31) | C30: 0 | D30: =D27*D29 | E30: =E27*E29 | F30: =F27*F29 | G30: =G27*G29 | H30: =H27*H29
A32: Sum explicit PV (FY27–FY31) | C32: =SUM(D30:H30)
A33: Terminal FCFF (FY31; capex=D&A) | C33: =(H17*Inputs!$D$37*(1-Inputs!$D$39)+H17*Inputs!$B$12-H17*Inputs!$B$13-H17*Inputs!$D$38*Inputs!$B$14)*(1+Inputs!$D$38)
A34: Terminal value (Gordon) | C34: =C33/(Inputs!$B$23-Inputs!$D$38)
A35: Discount factor t=5 | C35: =1/(1+Inputs!$B$23)^5
A36: PV of terminal value | C36: =C34*C35
A37: Enterprise value | C37: =C32+C36
A38: Less: net debt | C38: =-Inputs!$B$18
A39: Less: restructuring cash | C39: =-Inputs!$B$19
A40: Equity value | C40: =C37+C38+C39
A41: Shares (m) | C41: =Inputs!$B$20
A42: Value per share (USD) | C42: =C40/C41
A43: Value per share (AUD) | C43: =C42*Inputs!$B$21
A44: Terminal % of EV (memo) | C44: =C36/C37

Sheet S_AI
A1: AI Productivity Lag — segment DCF (USD m)
A3: Line | B3: FY25 | C3: FY26 | D3: FY27 | E3: FY28 | F3: FY29 | G3: FY30 | H3: FY31
A5: Behring revenue | B5: =Inputs!$B$3 | C5: =B5*(1+Inputs!$E$26) | D5: =C5*(1+Inputs!$E$27) | E5: =D5*(1+Inputs!$E$28) | F5: =E5*(1+Inputs!$E$29) | G5: =F5*(1+Inputs!$E$30) | H5: =G5*(1+Inputs!$E$31)
A6: Behring OR margin | B6: =Inputs!$B$7 | C6: =Inputs!$B$7+Inputs!$E$34*(1/6) | D6: =Inputs!$B$7+Inputs!$E$34*(2/6) | E6: =Inputs!$B$7+Inputs!$E$34*(3/6) | F6: =Inputs!$B$7+Inputs!$E$34*(4/6) | G6: =Inputs!$B$7+Inputs!$E$34*(5/6) | H6: =Inputs!$B$7+Inputs!$E$34*(6/6)
A7: Behring OR | B7: =B5*B6 | C7: =C5*C6 | D7: =D5*D6 | E7: =E5*E6 | F7: =F5*F6 | G7: =G5*G6 | H7: =H5*H6
A9: Seqirus revenue | B9: =Inputs!$B$4 | C9: =B9*(1+Inputs!$E$32) | D9: =C9*(1+Inputs!$E$32) | E9: =D9*(1+Inputs!$E$32) | F9: =E9*(1+Inputs!$E$32) | G9: =F9*(1+Inputs!$E$32) | H9: =G9*(1+Inputs!$E$32)
A10: Seqirus OR margin | B10: =Inputs!$B$8 | C10: =Inputs!$B$8+Inputs!$E$35*(1/6) | D10: =Inputs!$B$8+Inputs!$E$35*(2/6) | E10: =Inputs!$B$8+Inputs!$E$35*(3/6) | F10: =Inputs!$B$8+Inputs!$E$35*(4/6) | G10: =Inputs!$B$8+Inputs!$E$35*(5/6) | H10: =Inputs!$B$8+Inputs!$E$35*(6/6)
A11: Seqirus OR | B11: =B9*B10 | C11: =C9*C10 | D11: =D9*D10 | E11: =E9*E10 | F11: =F9*F10 | G11: =G9*G10 | H11: =H9*H10
A13: Vifor revenue | B13: =Inputs!$B$5 | C13: =B13*(1+Inputs!$E$33) | D13: =C13*(1+Inputs!$E$33) | E13: =D13*(1+Inputs!$E$33) | F13: =E13*(1+Inputs!$E$33) | G13: =F13*(1+Inputs!$E$33) | H13: =G13*(1+Inputs!$E$33)
A14: Vifor OR margin | B14: =Inputs!$B$9 | C14: =Inputs!$B$9+Inputs!$E$36*(1/6) | D14: =Inputs!$B$9+Inputs!$E$36*(2/6) | E14: =Inputs!$B$9+Inputs!$E$36*(3/6) | F14: =Inputs!$B$9+Inputs!$E$36*(4/6) | G14: =Inputs!$B$9+Inputs!$E$36*(5/6) | H14: =Inputs!$B$9+Inputs!$E$36*(6/6)
A15: Vifor OR | B15: =B13*B14 | C15: =C13*C14 | D15: =D13*D14 | E15: =E13*E14 | F15: =F13*F14 | G15: =G13*G14 | H15: =H13*H14
A17: Group revenue | B17: =B5+B9+B13 | C17: =C5+C9+C13 | D17: =D5+D9+D13 | E17: =E5+E9+E13 | F17: =F5+F9+F13 | G17: =G5+G9+G13 | H17: =H5+H9+H13
A18: Segment OR (sum) | B18: =B7+B11+B15 | C18: =C7+C11+C15 | D18: =D7+D11+D15 | E18: =E7+E11+E15 | F18: =F7+F11+F15 | G18: =G7+G11+G15 | H18: =H7+H11+H15
A19: Corporate / unalloc | B19: =Inputs!$B$10 | C19: =Inputs!$B$10*(1.005^1) | D19: =Inputs!$B$10*(1.005^2) | E19: =Inputs!$B$10*(1.005^3) | F19: =Inputs!$B$10*(1.005^4) | G19: =Inputs!$B$10*(1.005^5) | H19: =Inputs!$B$10*(1.005^6)
A20: Group EBIT | B20: =B18+B19 | C20: =C18+C19 | D20: =D18+D19 | E20: =E18+E19 | F20: =F18+F19 | G20: =G18+G19 | H20: =H18+H19
A21: Group EBIT margin (memo) | B21: =B20/B17 | C21: =C20/C17 | D21: =D20/D17 | E21: =E20/E17 | F21: =F20/F17 | G21: =G20/G17 | H21: =H20/H17
A23: NOPAT = EBIT x (1-tax) | C23: =C20*(1-Inputs!$E$39) | D23: =D20*(1-Inputs!$E$39) | E23: =E20*(1-Inputs!$E$39) | F23: =F20*(1-Inputs!$E$39) | G23: =G20*(1-Inputs!$E$39) | H23: =H20*(1-Inputs!$E$39)
A24: Plus: D&A | C24: =C17*Inputs!$B$12 | D24: =D17*Inputs!$B$12 | E24: =E17*Inputs!$B$12 | F24: =F17*Inputs!$B$12 | G24: =G17*Inputs!$B$12 | H24: =H17*Inputs!$B$12
A25: Less: capex (explicit yrs) | C25: =-C17*Inputs!$B$11 | D25: =-D17*Inputs!$B$11 | E25: =-E17*Inputs!$B$11 | F25: =-F17*Inputs!$B$11 | G25: =-G17*Inputs!$B$11 | H25: =-H17*Inputs!$B$11
A26: Less: WC change | C26: =-(C17-B17)*Inputs!$B$14 | D26: =-(D17-C17)*Inputs!$B$14 | E26: =-(E17-D17)*Inputs!$B$14 | F26: =-(F17-E17)*Inputs!$B$14 | G26: =-(G17-F17)*Inputs!$B$14 | H26: =-(H17-G17)*Inputs!$B$14
A27: FCFF | C27: =C23+C24+C25+C26 | D27: =D23+D24+D25+D26 | E27: =E23+E24+E25+E26 | F27: =F23+F24+F25+F26 | G27: =G23+G24+G25+G26 | H27: =H23+H24+H25+H26
A28: Mid-period t (FY26 excl.) | C28: 0 | D28: 0.5 | E28: 1.5 | F28: 2.5 | G28: 3.5 | H28: 4.5
A29: Discount factor | C29: =1/(1+Inputs!$B$23)^C28 | D29: =1/(1+Inputs!$B$23)^D28 | E29: =1/(1+Inputs!$B$23)^E28 | F29: =1/(1+Inputs!$B$23)^F28 | G29: =1/(1+Inputs!$B$23)^G28 | H29: =1/(1+Inputs!$B$23)^H28
A30: PV of FCFF (FY27–FY31) | C30: 0 | D30: =D27*D29 | E30: =E27*E29 | F30: =F27*F29 | G30: =G27*G29 | H30: =H27*H29
A32: Sum explicit PV (FY27–FY31) | C32: =SUM(D30:H30)
A33: Terminal FCFF (FY31; capex=D&A) | C33: =(H17*Inputs!$E$37*(1-Inputs!$E$39)+H17*Inputs!$B$12-H17*Inputs!$B$13-H17*Inputs!$E$38*Inputs!$B$14)*(1+Inputs!$E$38)
A34: Terminal value (Gordon) | C34: =C33/(Inputs!$B$23-Inputs!$E$38)
A35: Discount factor t=5 | C35: =1/(1+Inputs!$B$23)^5
A36: PV of terminal value | C36: =C34*C35
A37: Enterprise value | C37: =C32+C36
A38: Less: net debt | C38: =-Inputs!$B$18
A39: Less: restructuring cash | C39: =-Inputs!$B$19
A40: Equity value | C40: =C37+C38+C39
A41: Shares (m) | C41: =Inputs!$B$20
A42: Value per share (USD) | C42: =C40/C41
A43: Value per share (AUD) | C43: =C42*Inputs!$B$21
A44: Terminal % of EV (memo) | C44: =C36/C37

Sheet S_Disorderly
A1: Disorderly Climate — segment DCF (USD m)
A3: Line | B3: FY25 | C3: FY26 | D3: FY27 | E3: FY28 | F3: FY29 | G3: FY30 | H3: FY31
A5: Behring revenue | B5: =Inputs!$B$3 | C5: =B5*(1+Inputs!$F$26) | D5: =C5*(1+Inputs!$F$27) | E5: =D5*(1+Inputs!$F$28) | F5: =E5*(1+Inputs!$F$29) | G5: =F5*(1+Inputs!$F$30) | H5: =G5*(1+Inputs!$F$31)
A6: Behring OR margin | B6: =Inputs!$B$7 | C6: =Inputs!$B$7+Inputs!$F$34*(1/6) | D6: =Inputs!$B$7+Inputs!$F$34*(2/6) | E6: =Inputs!$B$7+Inputs!$F$34*(3/6) | F6: =Inputs!$B$7+Inputs!$F$34*(4/6) | G6: =Inputs!$B$7+Inputs!$F$34*(5/6) | H6: =Inputs!$B$7+Inputs!$F$34*(6/6)
A7: Behring OR | B7: =B5*B6 | C7: =C5*C6 | D7: =D5*D6 | E7: =E5*E6 | F7: =F5*F6 | G7: =G5*G6 | H7: =H5*H6
A9: Seqirus revenue | B9: =Inputs!$B$4 | C9: =B9*(1+Inputs!$F$32) | D9: =C9*(1+Inputs!$F$32) | E9: =D9*(1+Inputs!$F$32) | F9: =E9*(1+Inputs!$F$32) | G9: =F9*(1+Inputs!$F$32) | H9: =G9*(1+Inputs!$F$32)
A10: Seqirus OR margin | B10: =Inputs!$B$8 | C10: =Inputs!$B$8+Inputs!$F$35*(1/6) | D10: =Inputs!$B$8+Inputs!$F$35*(2/6) | E10: =Inputs!$B$8+Inputs!$F$35*(3/6) | F10: =Inputs!$B$8+Inputs!$F$35*(4/6) | G10: =Inputs!$B$8+Inputs!$F$35*(5/6) | H10: =Inputs!$B$8+Inputs!$F$35*(6/6)
A11: Seqirus OR | B11: =B9*B10 | C11: =C9*C10 | D11: =D9*D10 | E11: =E9*E10 | F11: =F9*F10 | G11: =G9*G10 | H11: =H9*H10
A13: Vifor revenue | B13: =Inputs!$B$5 | C13: =B13*(1+Inputs!$F$33) | D13: =C13*(1+Inputs!$F$33) | E13: =D13*(1+Inputs!$F$33) | F13: =E13*(1+Inputs!$F$33) | G13: =F13*(1+Inputs!$F$33) | H13: =G13*(1+Inputs!$F$33)
A14: Vifor OR margin | B14: =Inputs!$B$9 | C14: =Inputs!$B$9+Inputs!$F$36*(1/6) | D14: =Inputs!$B$9+Inputs!$F$36*(2/6) | E14: =Inputs!$B$9+Inputs!$F$36*(3/6) | F14: =Inputs!$B$9+Inputs!$F$36*(4/6) | G14: =Inputs!$B$9+Inputs!$F$36*(5/6) | H14: =Inputs!$B$9+Inputs!$F$36*(6/6)
A15: Vifor OR | B15: =B13*B14 | C15: =C13*C14 | D15: =D13*D14 | E15: =E13*E14 | F15: =F13*F14 | G15: =G13*G14 | H15: =H13*H14
A17: Group revenue | B17: =B5+B9+B13 | C17: =C5+C9+C13 | D17: =D5+D9+D13 | E17: =E5+E9+E13 | F17: =F5+F9+F13 | G17: =G5+G9+G13 | H17: =H5+H9+H13
A18: Segment OR (sum) | B18: =B7+B11+B15 | C18: =C7+C11+C15 | D18: =D7+D11+D15 | E18: =E7+E11+E15 | F18: =F7+F11+F15 | G18: =G7+G11+G15 | H18: =H7+H11+H15
A19: Corporate / unalloc | B19: =Inputs!$B$10 | C19: =Inputs!$B$10*(1.005^1) | D19: =Inputs!$B$10*(1.005^2) | E19: =Inputs!$B$10*(1.005^3) | F19: =Inputs!$B$10*(1.005^4) | G19: =Inputs!$B$10*(1.005^5) | H19: =Inputs!$B$10*(1.005^6)
A20: Group EBIT | B20: =B18+B19 | C20: =C18+C19 | D20: =D18+D19 | E20: =E18+E19 | F20: =F18+F19 | G20: =G18+G19 | H20: =H18+H19
A21: Group EBIT margin (memo) | B21: =B20/B17 | C21: =C20/C17 | D21: =D20/D17 | E21: =E20/E17 | F21: =F20/F17 | G21: =G20/G17 | H21: =H20/H17
A23: NOPAT = EBIT x (1-tax) | C23: =C20*(1-Inputs!$F$39) | D23: =D20*(1-Inputs!$F$39) | E23: =E20*(1-Inputs!$F$39) | F23: =F20*(1-Inputs!$F$39) | G23: =G20*(1-Inputs!$F$39) | H23: =H20*(1-Inputs!$F$39)
A24: Plus: D&A | C24: =C17*Inputs!$B$12 | D24: =D17*Inputs!$B$12 | E24: =E17*Inputs!$B$12 | F24: =F17*Inputs!$B$12 | G24: =G17*Inputs!$B$12 | H24: =H17*Inputs!$B$12
A25: Less: capex (explicit yrs) | C25: =-C17*Inputs!$B$11 | D25: =-D17*Inputs!$B$11 | E25: =-E17*Inputs!$B$11 | F25: =-F17*Inputs!$B$11 | G25: =-G17*Inputs!$B$11 | H25: =-H17*Inputs!$B$11
A26: Less: WC change | C26: =-(C17-B17)*Inputs!$B$14 | D26: =-(D17-C17)*Inputs!$B$14 | E26: =-(E17-D17)*Inputs!$B$14 | F26: =-(F17-E17)*Inputs!$B$14 | G26: =-(G17-F17)*Inputs!$B$14 | H26: =-(H17-G17)*Inputs!$B$14
A27: FCFF | C27: =C23+C24+C25+C26 | D27: =D23+D24+D25+D26 | E27: =E23+E24+E25+E26 | F27: =F23+F24+F25+F26 | G27: =G23+G24+G25+G26 | H27: =H23+H24+H25+H26
A28: Mid-period t (FY26 excl.) | C28: 0 | D28: 0.5 | E28: 1.5 | F28: 2.5 | G28: 3.5 | H28: 4.5
A29: Discount factor | C29: =1/(1+Inputs!$B$23)^C28 | D29: =1/(1+Inputs!$B$23)^D28 | E29: =1/(1+Inputs!$B$23)^E28 | F29: =1/(1+Inputs!$B$23)^F28 | G29: =1/(1+Inputs!$B$23)^G28 | H29: =1/(1+Inputs!$B$23)^H28
A30: PV of FCFF (FY27–FY31) | C30: 0 | D30: =D27*D29 | E30: =E27*E29 | F30: =F27*F29 | G30: =G27*G29 | H30: =H27*H29
A32: Sum explicit PV (FY27–FY31) | C32: =SUM(D30:H30)
A33: Terminal FCFF (FY31; capex=D&A) | C33: =(H17*Inputs!$F$37*(1-Inputs!$F$39)+H17*Inputs!$B$12-H17*Inputs!$B$13-H17*Inputs!$F$38*Inputs!$B$14)*(1+Inputs!$F$38)
A34: Terminal value (Gordon) | C34: =C33/(Inputs!$B$23-Inputs!$F$38)
A35: Discount factor t=5 | C35: =1/(1+Inputs!$B$23)^5
A36: PV of terminal value | C36: =C34*C35
A37: Enterprise value | C37: =C32+C36
A38: Less: net debt | C38: =-Inputs!$B$18
A39: Less: restructuring cash | C39: =-Inputs!$B$19
A40: Equity value | C40: =C37+C38+C39
A41: Shares (m) | C41: =Inputs!$B$20
A42: Value per share (USD) | C42: =C40/C41
A43: Value per share (AUD) | C43: =C42*Inputs!$B$21
A44: Terminal % of EV (memo) | C44: =C36/C37

Sheet S_Fragmentation
A1: Fragmentation — segment DCF (USD m)
A3: Line | B3: FY25 | C3: FY26 | D3: FY27 | E3: FY28 | F3: FY29 | G3: FY30 | H3: FY31
A5: Behring revenue | B5: =Inputs!$B$3 | C5: =B5*(1+Inputs!$G$26) | D5: =C5*(1+Inputs!$G$27) | E5: =D5*(1+Inputs!$G$28) | F5: =E5*(1+Inputs!$G$29) | G5: =F5*(1+Inputs!$G$30) | H5: =G5*(1+Inputs!$G$31)
A6: Behring OR margin | B6: =Inputs!$B$7 | C6: =Inputs!$B$7+Inputs!$G$34*(1/6) | D6: =Inputs!$B$7+Inputs!$G$34*(2/6) | E6: =Inputs!$B$7+Inputs!$G$34*(3/6) | F6: =Inputs!$B$7+Inputs!$G$34*(4/6) | G6: =Inputs!$B$7+Inputs!$G$34*(5/6) | H6: =Inputs!$B$7+Inputs!$G$34*(6/6)
A7: Behring OR | B7: =B5*B6 | C7: =C5*C6 | D7: =D5*D6 | E7: =E5*E6 | F7: =F5*F6 | G7: =G5*G6 | H7: =H5*H6
A9: Seqirus revenue | B9: =Inputs!$B$4 | C9: =B9*(1+Inputs!$G$32) | D9: =C9*(1+Inputs!$G$32) | E9: =D9*(1+Inputs!$G$32) | F9: =E9*(1+Inputs!$G$32) | G9: =F9*(1+Inputs!$G$32) | H9: =G9*(1+Inputs!$G$32)
A10: Seqirus OR margin | B10: =Inputs!$B$8 | C10: =Inputs!$B$8+Inputs!$G$35*(1/6) | D10: =Inputs!$B$8+Inputs!$G$35*(2/6) | E10: =Inputs!$B$8+Inputs!$G$35*(3/6) | F10: =Inputs!$B$8+Inputs!$G$35*(4/6) | G10: =Inputs!$B$8+Inputs!$G$35*(5/6) | H10: =Inputs!$B$8+Inputs!$G$35*(6/6)
A11: Seqirus OR | B11: =B9*B10 | C11: =C9*C10 | D11: =D9*D10 | E11: =E9*E10 | F11: =F9*F10 | G11: =G9*G10 | H11: =H9*H10
A13: Vifor revenue | B13: =Inputs!$B$5 | C13: =B13*(1+Inputs!$G$33) | D13: =C13*(1+Inputs!$G$33) | E13: =D13*(1+Inputs!$G$33) | F13: =E13*(1+Inputs!$G$33) | G13: =F13*(1+Inputs!$G$33) | H13: =G13*(1+Inputs!$G$33)
A14: Vifor OR margin | B14: =Inputs!$B$9 | C14: =Inputs!$B$9+Inputs!$G$36*(1/6) | D14: =Inputs!$B$9+Inputs!$G$36*(2/6) | E14: =Inputs!$B$9+Inputs!$G$36*(3/6) | F14: =Inputs!$B$9+Inputs!$G$36*(4/6) | G14: =Inputs!$B$9+Inputs!$G$36*(5/6) | H14: =Inputs!$B$9+Inputs!$G$36*(6/6)
A15: Vifor OR | B15: =B13*B14 | C15: =C13*C14 | D15: =D13*D14 | E15: =E13*E14 | F15: =F13*F14 | G15: =G13*G14 | H15: =H13*H14
A17: Group revenue | B17: =B5+B9+B13 | C17: =C5+C9+C13 | D17: =D5+D9+D13 | E17: =E5+E9+E13 | F17: =F5+F9+F13 | G17: =G5+G9+G13 | H17: =H5+H9+H13
A18: Segment OR (sum) | B18: =B7+B11+B15 | C18: =C7+C11+C15 | D18: =D7+D11+D15 | E18: =E7+E11+E15 | F18: =F7+F11+F15 | G18: =G7+G11+G15 | H18: =H7+H11+H15
A19: Corporate / unalloc | B19: =Inputs!$B$10 | C19: =Inputs!$B$10*(1.005^1) | D19: =Inputs!$B$10*(1.005^2) | E19: =Inputs!$B$10*(1.005^3) | F19: =Inputs!$B$10*(1.005^4) | G19: =Inputs!$B$10*(1.005^5) | H19: =Inputs!$B$10*(1.005^6)
A20: Group EBIT | B20: =B18+B19 | C20: =C18+C19 | D20: =D18+D19 | E20: =E18+E19 | F20: =F18+F19 | G20: =G18+G19 | H20: =H18+H19
A21: Group EBIT margin (memo) | B21: =B20/B17 | C21: =C20/C17 | D21: =D20/D17 | E21: =E20/E17 | F21: =F20/F17 | G21: =G20/G17 | H21: =H20/H17
A23: NOPAT = EBIT x (1-tax) | C23: =C20*(1-Inputs!$G$39) | D23: =D20*(1-Inputs!$G$39) | E23: =E20*(1-Inputs!$G$39) | F23: =F20*(1-Inputs!$G$39) | G23: =G20*(1-Inputs!$G$39) | H23: =H20*(1-Inputs!$G$39)
A24: Plus: D&A | C24: =C17*Inputs!$B$12 | D24: =D17*Inputs!$B$12 | E24: =E17*Inputs!$B$12 | F24: =F17*Inputs!$B$12 | G24: =G17*Inputs!$B$12 | H24: =H17*Inputs!$B$12
A25: Less: capex (explicit yrs) | C25: =-C17*Inputs!$B$11 | D25: =-D17*Inputs!$B$11 | E25: =-E17*Inputs!$B$11 | F25: =-F17*Inputs!$B$11 | G25: =-G17*Inputs!$B$11 | H25: =-H17*Inputs!$B$11
A26: Less: WC change | C26: =-(C17-B17)*Inputs!$B$14 | D26: =-(D17-C17)*Inputs!$B$14 | E26: =-(E17-D17)*Inputs!$B$14 | F26: =-(F17-E17)*Inputs!$B$14 | G26: =-(G17-F17)*Inputs!$B$14 | H26: =-(H17-G17)*Inputs!$B$14
A27: FCFF | C27: =C23+C24+C25+C26 | D27: =D23+D24+D25+D26 | E27: =E23+E24+E25+E26 | F27: =F23+F24+F25+F26 | G27: =G23+G24+G25+G26 | H27: =H23+H24+H25+H26
A28: Mid-period t (FY26 excl.) | C28: 0 | D28: 0.5 | E28: 1.5 | F28: 2.5 | G28: 3.5 | H28: 4.5
A29: Discount factor | C29: =1/(1+Inputs!$B$23)^C28 | D29: =1/(1+Inputs!$B$23)^D28 | E29: =1/(1+Inputs!$B$23)^E28 | F29: =1/(1+Inputs!$B$23)^F28 | G29: =1/(1+Inputs!$B$23)^G28 | H29: =1/(1+Inputs!$B$23)^H28
A30: PV of FCFF (FY27–FY31) | C30: 0 | D30: =D27*D29 | E30: =E27*E29 | F30: =F27*F29 | G30: =G27*G29 | H30: =H27*H29
A32: Sum explicit PV (FY27–FY31) | C32: =SUM(D30:H30)
A33: Terminal FCFF (FY31; capex=D&A) | C33: =(H17*Inputs!$G$37*(1-Inputs!$G$39)+H17*Inputs!$B$12-H17*Inputs!$B$13-H17*Inputs!$G$38*Inputs!$B$14)*(1+Inputs!$G$38)
A34: Terminal value (Gordon) | C34: =C33/(Inputs!$B$23-Inputs!$G$38)
A35: Discount factor t=5 | C35: =1/(1+Inputs!$B$23)^5
A36: PV of terminal value | C36: =C34*C35
A37: Enterprise value | C37: =C32+C36
A38: Less: net debt | C38: =-Inputs!$B$18
A39: Less: restructuring cash | C39: =-Inputs!$B$19
A40: Equity value | C40: =C37+C38+C39
A41: Shares (m) | C41: =Inputs!$B$20
A42: Value per share (USD) | C42: =C40/C41
A43: Value per share (AUD) | C43: =C42*Inputs!$B$21
A44: Terminal % of EV (memo) | C44: =C36/C37

Sheet S_Stagflation
A1: Stagflation Persists — segment DCF (USD m)
A3: Line | B3: FY25 | C3: FY26 | D3: FY27 | E3: FY28 | F3: FY29 | G3: FY30 | H3: FY31
A5: Behring revenue | B5: =Inputs!$B$3 | C5: =B5*(1+Inputs!$H$26) | D5: =C5*(1+Inputs!$H$27) | E5: =D5*(1+Inputs!$H$28) | F5: =E5*(1+Inputs!$H$29) | G5: =F5*(1+Inputs!$H$30) | H5: =G5*(1+Inputs!$H$31)
A6: Behring OR margin | B6: =Inputs!$B$7 | C6: =Inputs!$B$7+Inputs!$H$34*(1/6) | D6: =Inputs!$B$7+Inputs!$H$34*(2/6) | E6: =Inputs!$B$7+Inputs!$H$34*(3/6) | F6: =Inputs!$B$7+Inputs!$H$34*(4/6) | G6: =Inputs!$B$7+Inputs!$H$34*(5/6) | H6: =Inputs!$B$7+Inputs!$H$34*(6/6)
A7: Behring OR | B7: =B5*B6 | C7: =C5*C6 | D7: =D5*D6 | E7: =E5*E6 | F7: =F5*F6 | G7: =G5*G6 | H7: =H5*H6
A9: Seqirus revenue | B9: =Inputs!$B$4 | C9: =B9*(1+Inputs!$H$32) | D9: =C9*(1+Inputs!$H$32) | E9: =D9*(1+Inputs!$H$32) | F9: =E9*(1+Inputs!$H$32) | G9: =F9*(1+Inputs!$H$32) | H9: =G9*(1+Inputs!$H$32)
A10: Seqirus OR margin | B10: =Inputs!$B$8 | C10: =Inputs!$B$8+Inputs!$H$35*(1/6) | D10: =Inputs!$B$8+Inputs!$H$35*(2/6) | E10: =Inputs!$B$8+Inputs!$H$35*(3/6) | F10: =Inputs!$B$8+Inputs!$H$35*(4/6) | G10: =Inputs!$B$8+Inputs!$H$35*(5/6) | H10: =Inputs!$B$8+Inputs!$H$35*(6/6)
A11: Seqirus OR | B11: =B9*B10 | C11: =C9*C10 | D11: =D9*D10 | E11: =E9*E10 | F11: =F9*F10 | G11: =G9*G10 | H11: =H9*H10
A13: Vifor revenue | B13: =Inputs!$B$5 | C13: =B13*(1+Inputs!$H$33) | D13: =C13*(1+Inputs!$H$33) | E13: =D13*(1+Inputs!$H$33) | F13: =E13*(1+Inputs!$H$33) | G13: =F13*(1+Inputs!$H$33) | H13: =G13*(1+Inputs!$H$33)
A14: Vifor OR margin | B14: =Inputs!$B$9 | C14: =Inputs!$B$9+Inputs!$H$36*(1/6) | D14: =Inputs!$B$9+Inputs!$H$36*(2/6) | E14: =Inputs!$B$9+Inputs!$H$36*(3/6) | F14: =Inputs!$B$9+Inputs!$H$36*(4/6) | G14: =Inputs!$B$9+Inputs!$H$36*(5/6) | H14: =Inputs!$B$9+Inputs!$H$36*(6/6)
A15: Vifor OR | B15: =B13*B14 | C15: =C13*C14 | D15: =D13*D14 | E15: =E13*E14 | F15: =F13*F14 | G15: =G13*G14 | H15: =H13*H14
A17: Group revenue | B17: =B5+B9+B13 | C17: =C5+C9+C13 | D17: =D5+D9+D13 | E17: =E5+E9+E13 | F17: =F5+F9+F13 | G17: =G5+G9+G13 | H17: =H5+H9+H13
A18: Segment OR (sum) | B18: =B7+B11+B15 | C18: =C7+C11+C15 | D18: =D7+D11+D15 | E18: =E7+E11+E15 | F18: =F7+F11+F15 | G18: =G7+G11+G15 | H18: =H7+H11+H15
A19: Corporate / unalloc | B19: =Inputs!$B$10 | C19: =Inputs!$B$10*(1.005^1) | D19: =Inputs!$B$10*(1.005^2) | E19: =Inputs!$B$10*(1.005^3) | F19: =Inputs!$B$10*(1.005^4) | G19: =Inputs!$B$10*(1.005^5) | H19: =Inputs!$B$10*(1.005^6)
A20: Group EBIT | B20: =B18+B19 | C20: =C18+C19 | D20: =D18+D19 | E20: =E18+E19 | F20: =F18+F19 | G20: =G18+G19 | H20: =H18+H19
A21: Group EBIT margin (memo) | B21: =B20/B17 | C21: =C20/C17 | D21: =D20/D17 | E21: =E20/E17 | F21: =F20/F17 | G21: =G20/G17 | H21: =H20/H17
A23: NOPAT = EBIT x (1-tax) | C23: =C20*(1-Inputs!$H$39) | D23: =D20*(1-Inputs!$H$39) | E23: =E20*(1-Inputs!$H$39) | F23: =F20*(1-Inputs!$H$39) | G23: =G20*(1-Inputs!$H$39) | H23: =H20*(1-Inputs!$H$39)
A24: Plus: D&A | C24: =C17*Inputs!$B$12 | D24: =D17*Inputs!$B$12 | E24: =E17*Inputs!$B$12 | F24: =F17*Inputs!$B$12 | G24: =G17*Inputs!$B$12 | H24: =H17*Inputs!$B$12
A25: Less: capex (explicit yrs) | C25: =-C17*Inputs!$B$11 | D25: =-D17*Inputs!$B$11 | E25: =-E17*Inputs!$B$11 | F25: =-F17*Inputs!$B$11 | G25: =-G17*Inputs!$B$11 | H25: =-H17*Inputs!$B$11
A26: Less: WC change | C26: =-(C17-B17)*Inputs!$B$14 | D26: =-(D17-C17)*Inputs!$B$14 | E26: =-(E17-D17)*Inputs!$B$14 | F26: =-(F17-E17)*Inputs!$B$14 | G26: =-(G17-F17)*Inputs!$B$14 | H26: =-(H17-G17)*Inputs!$B$14
A27: FCFF | C27: =C23+C24+C25+C26 | D27: =D23+D24+D25+D26 | E27: =E23+E24+E25+E26 | F27: =F23+F24+F25+F26 | G27: =G23+G24+G25+G26 | H27: =H23+H24+H25+H26
A28: Mid-period t (FY26 excl.) | C28: 0 | D28: 0.5 | E28: 1.5 | F28: 2.5 | G28: 3.5 | H28: 4.5
A29: Discount factor | C29: =1/(1+Inputs!$B$23)^C28 | D29: =1/(1+Inputs!$B$23)^D28 | E29: =1/(1+Inputs!$B$23)^E28 | F29: =1/(1+Inputs!$B$23)^F28 | G29: =1/(1+Inputs!$B$23)^G28 | H29: =1/(1+Inputs!$B$23)^H28
A30: PV of FCFF (FY27–FY31) | C30: 0 | D30: =D27*D29 | E30: =E27*E29 | F30: =F27*F29 | G30: =G27*G29 | H30: =H27*H29
A32: Sum explicit PV (FY27–FY31) | C32: =SUM(D30:H30)
A33: Terminal FCFF (FY31; capex=D&A) | C33: =(H17*Inputs!$H$37*(1-Inputs!$H$39)+H17*Inputs!$B$12-H17*Inputs!$B$13-H17*Inputs!$H$38*Inputs!$B$14)*(1+Inputs!$H$38)
A34: Terminal value (Gordon) | C34: =C33/(Inputs!$B$23-Inputs!$H$38)
A35: Discount factor t=5 | C35: =1/(1+Inputs!$B$23)^5
A36: PV of terminal value | C36: =C34*C35
A37: Enterprise value | C37: =C32+C36
A38: Less: net debt | C38: =-Inputs!$B$18
A39: Less: restructuring cash | C39: =-Inputs!$B$19
A40: Equity value | C40: =C37+C38+C39
A41: Shares (m) | C41: =Inputs!$B$20
A42: Value per share (USD) | C42: =C40/C41
A43: Value per share (AUD) | C43: =C42*Inputs!$B$21
A44: Terminal % of EV (memo) | C44: =C36/C37

Sheet Notes
A1: Methodology notes (v2)
A3: v2 change. Terminal capex set equal to D&A (steady-state reinvestment consistency). v1 ran terminal capex 4.5% < D&A 6%, inflating perpetual FCFF by ~1.5% of revenue forever; correcting it trims every scenario ~5%. Explicit-period capex stays 4.5% (near-term guidance; D&A>capex there reflects Vifor/Behring intangible amortisation, which legitimately exceeds capex until it runs off).
A4: Engine. Each scenario tab replicates the v3 Muddle Through segment DCF (Behring J-curve + Seqirus/Vifor CAGR; linear OR-margin glide to FY31; corporate +0.5%/yr; FCFF = NOPAT + D&A − capex − ΔWC; explicit FY27–FY31 mid-period discounted; Gordon terminal off FY31). After the capex fix, the MT tab gives USD 134.52 / AUD 203.83 (v3 standalone is USD 141.78 pre-fix — v3 should get the same terminal-capex correction → a 'v4').
A5: Base. All scenarios anchor off v3 (terminal-margin fix binding; Behring J-curve FY26 −1% → 5.5%; Behring peer-gap uplift +150bps in MT, full +250bps reserved for Orderly). Shared base inputs identical across scenarios on the Inputs tab.
A6: Per-scenario drivers (Inputs tab, yellow): Behring 6-year growth path, Seqirus & Vifor CAGR, the three segment margin uplifts, terminal EBIT margin, terminal growth g, effective tax. The only levers that move between scenarios; everything else links by formula.
A7: Calibration logic (CSL defensive — scenarios act on margins/policy, not volumes):
A8: Orderly: benign macro, collection-cost inflation eases → full +250bps Behring closure, faster J-curve, terminal margin 31.5%, g 3.25%.
A9: AI Productivity Lag: white-collar wage containment a mild margin tailwind; softer macro, lower terminal g 2.875%. Marginally below MT.
A10: Disorderly Climate: carbon-cost pass-through compresses fractionation/cold-chain margins; Seqirus vaccine demand a partial offset. Terminal margin 28%, g 2.75%.
A11: Fragmentation: China Ig access + supply-chain localisation friction; closure stalls (uplift 0), effective tax 20%. Terminal margin 28.2%, g 2.75%.
A12: Stagflation: worst margin case — donor-collection wage inflation + payor pricing; closure reverses (Behring −150bps). Terminal margin 26.5%, g held 3% (nominal).
A13: §3.5.7 market-implied. See the dedicated tab: single-lever reverse-DCF shows the market implies β≈1.7–1.8 / terminal margin ~13% / g negative — none plausible alone, so the gap is a blend (or genuine under-pricing).
... A15: Status. Calibration draft for Stephen's sign-off (25 June 2026). Thesis + discussion document deferred per agreed scope. Open: β/cost-of-equity reality check; backport terminal-capex fix to the v3 standalone workbook.
