Workbook

Sheet Cover
A1: CSL Limited — cross-scenario valuation (off v3 Muddle Through base)
A2: Six-scenario distribution • USD functional, AUD at spot • 25 June 2026 • Reid Advisory
A4: Scenario | B4: Per share USD | C4: Per share AUD | D4: vs Market | E4: vs Muddle Through | F4: Terminal % EV
A5: Orderly Convergence | B5: ='S_Orderly'!C42 | C5: ='S_Orderly'!C43 | D5: ='S_Orderly'!C43/Inputs!$B$21-1 | E5: ='S_Orderly'!C42/'S_Muddle'!C42-1 | F5: ='S_Orderly'!C44
A6: Muddle Through | B6: ='S_Muddle'!C42 | C6: ='S_Muddle'!C43 | D6: ='S_Muddle'!C43/Inputs!$B$21-1 | E6: ='S_Muddle'!C42/'S_Muddle'!C42-1 | F6: ='S_Muddle'!C44
A7: AI Productivity Lag | B7: ='S_AI'!C42 | C7: ='S_AI'!C43 | D7: ='S_AI'!C43/Inputs!$B$21-1 | E7: ='S_AI'!C42/'S_Muddle'!C42-1 | F7: ='S_AI'!C44
A8: Disorderly Climate | B8: ='S_Disorderly'!C42 | C8: ='S_Disorderly'!C43 | D8: ='S_Disorderly'!C43/Inputs!$B$21-1 | E8: ='S_Disorderly'!C42/'S_Muddle'!C42-1 | F8: ='S_Disorderly'!C44
A9: Fragmentation | B9: ='S_Fragmentation'!C42 | C9: ='S_Fragmentation'!C43 | D9: ='S_Fragmentation'!C43/Inputs!$B$21-1 | E9: ='S_Fragmentation'!C42/'S_Muddle'!C42-1 | F9: ='S_Fragmentation'!C44
A10: Stagflation Persists | B10: ='S_Stagflation'!C42 | C10: ='S_Stagflation'!C43 | D10: ='S_Stagflation'!C43/Inputs!$B$21-1 | E10: ='S_Stagflation'!C42/'S_Muddle'!C42-1 | F10: ='S_Stagflation'!C44
A12: Upside (Orderly − MT), USD | B12: ='S_Orderly'!C42-'S_Muddle'!C42
A13: Downside (MT − Stagflation), USD | B13: ='S_Muddle'!C42-'S_Stagflation'!C42
A14: Asymmetry ratio (down/up) | B14: =B13/B12
A16: Observation 1 — Defensive shape. Asymmetry ~1.3x: downside modestly exceeds upside, far below DNL's cyclical 4.05x and below WBC's 1.83x. Plasma demand is volume-inelastic, so scenarios transmit through margins (donor-collection wages, energy/carbon cost, payor pricing) and policy, not volumes.
A17: Observation 2 — Whole distribution sits above market. Even the Stagflation boundary (~AUD 170) is well above market (AUD 105.53). Per methodology §16 the market is implicitly pricing a state more bearish than the framework's downside boundary — a genuine through-cycle disagreement, not a calibration error (see v3 reforecast notes).
A18: Observation 3 — Terminal-heavy. Terminal value is ~75–78% of EV across scenarios (a long-duration compounder at 30% terminal margin, 3% g, 8.75% Re). Sensitivity concentrates in terminal margin and g; the >70% terminal-share validator fires structurally (cf. DNL Phase 3.5).
A19: Single discount rate 8.75% (Rf 4.5% + β0.85 × ERP 5.0%) held across all scenarios per the single-WACC discipline; scenario risk is priced in the cash-flow paths, not the rate.

Sheet Inputs
A1: CSL scenarios — shared base + per-scenario drivers
A2: Shared base (identical across scenarios)
A3: Behring revenue FY25 (USD m) | B3: 11158
A4: Seqirus revenue FY25 (USD m) | B4: 2166
A5: Vifor revenue FY25 (USD m) | B5: 2234
A6: Group revenue FY25 (USD m) | B6: 15558
A7: Behring OR margin FY25 | B7: 0.422
A8: Seqirus OR margin FY25 | B8: 0.474
A9: Vifor OR margin FY25 | B9: 0.491
A10: Corporate/unalloc FY25 (USD m) | B10: -2559
A11: Capex / revenue | B11: 0.045
A12: D&A / revenue | B12: 0.06
A13: Working-capital change / Δrevenue | B13: 0.1
A14: Risk-free rate (10y UST) | B14: 0.045
... A21: Market price (AUD) | B21: 105.53
A22: Cost of equity Re = Rf + beta x ERP (derived) | B22: =B14+B16*B15
A24: Driver | C24: Orderly Convergence | D24: Muddle Through | E24: AI Productivity Lag | F24: Disorderly Climate | G24: Fragmentation | H24: Stagflation Persists
A25: Behring growth FY26 | C25: -0.005 | D25: -0.01 | E25: -0.01 | F25: -0.01 | G25: -0.015 | H25: -0.015
A26: Behring growth FY27 | C26: 0.04 | D26: 0.025 | E26: 0.025 | F26: 0.02 | G26: 0.015 | H26: 0.01
A27: Behring growth FY28 | C27: 0.055 | D27: 0.045 | E27: 0.045 | F27: 0.035 | G27: 0.03 | H27: 0.025
A28: Behring growth FY29 | C28: 0.065 | D28: 0.055 | E28: 0.05 | F28: 0.045 | G28: 0.04 | H28: 0.035
A29: Behring growth FY30 | C29: 0.065 | D29: 0.055 | E29: 0.05 | F29: 0.045 | G29: 0.04 | H29: 0.035
A30: Behring growth FY31 | C30: 0.065 | D30: 0.055 | E30: 0.05 | F30: 0.045 | G30: 0.04 | H30: 0.035
A31: Seqirus revenue CAGR | C31: 0.025 | D31: 0.02 | E31: 0.02 | F31: 0.03 | G31: 0.015 | H31: 0.01
A32: Vifor revenue CAGR | C32: 0.085 | D32: 0.07 | E32: 0.065 | F32: 0.05 | G32: 0.055 | H32: 0.04
A33: Behring margin uplift (cum, FY31) | C33: 0.025 | D33: 0.015 | E33: 0.0175 | F33: -0.005 | G33: 0 | H33: -0.015
A34: Seqirus margin uplift (cum, FY31) | C34: 0.015 | D34: 0.01 | E34: 0.01 | F34: 0.005 | G34: 0 | H34: -0.005
A35: Vifor margin uplift (cum, FY31) | C35: 0.015 | D35: 0.01 | E35: 0.01 | F35: 0 | G35: 0 | H35: -0.005
A36: Terminal EBIT margin | C36: 0.315 | D36: 0.3 | E36: 0.3025 | F36: 0.28 | G36: 0.282 | H36: 0.265
... A38: Effective tax rate | C38: 0.19 | D38: 0.19 | E38: 0.19 | F38: 0.19 | G38: 0.2 | H38: 0.19

Sheet S_Orderly
A1: Orderly Convergence — segment DCF (USD m)
A3: Line | B3: FY25 | C3: FY26 | D3: FY27 | E3: FY28 | F3: FY29 | G3: FY30 | H3: FY31
A5: Behring revenue | B5: =Inputs!$B$3 | C5: =B5*(1+Inputs!$C$25) | D5: =C5*(1+Inputs!$C$26) | E5: =D5*(1+Inputs!$C$27) | F5: =E5*(1+Inputs!$C$28) | G5: =F5*(1+Inputs!$C$29) | H5: =G5*(1+Inputs!$C$30)
A6: Behring OR margin | B6: =Inputs!$B$7 | C6: =Inputs!$B$7+Inputs!$C$33*(1/6) | D6: =Inputs!$B$7+Inputs!$C$33*(2/6) | E6: =Inputs!$B$7+Inputs!$C$33*(3/6) | F6: =Inputs!$B$7+Inputs!$C$33*(4/6) | G6: =Inputs!$B$7+Inputs!$C$33*(5/6) | H6: =Inputs!$B$7+Inputs!$C$33*(6/6)
A7: Behring OR | B7: =B5*B6 | C7: =C5*C6 | D7: =D5*D6 | E7: =E5*E6 | F7: =F5*F6 | G7: =G5*G6 | H7: =H5*H6
A9: Seqirus revenue | B9: =Inputs!$B$4 | C9: =B9*(1+Inputs!$C$31) | D9: =C9*(1+Inputs!$C$31) | E9: =D9*(1+Inputs!$C$31) | F9: =E9*(1+Inputs!$C$31) | G9: =F9*(1+Inputs!$C$31) | H9: =G9*(1+Inputs!$C$31)
A10: Seqirus OR margin | B10: =Inputs!$B$8 | C10: =Inputs!$B$8+Inputs!$C$34*(1/6) | D10: =Inputs!$B$8+Inputs!$C$34*(2/6) | E10: =Inputs!$B$8+Inputs!$C$34*(3/6) | F10: =Inputs!$B$8+Inputs!$C$34*(4/6) | G10: =Inputs!$B$8+Inputs!$C$34*(5/6) | H10: =Inputs!$B$8+Inputs!$C$34*(6/6)
A11: Seqirus OR | B11: =B9*B10 | C11: =C9*C10 | D11: =D9*D10 | E11: =E9*E10 | F11: =F9*F10 | G11: =G9*G10 | H11: =H9*H10
A13: Vifor revenue | B13: =Inputs!$B$5 | C13: =B13*(1+Inputs!$C$32) | D13: =C13*(1+Inputs!$C$32) | E13: =D13*(1+Inputs!$C$32) | F13: =E13*(1+Inputs!$C$32) | G13: =F13*(1+Inputs!$C$32) | H13: =G13*(1+Inputs!$C$32)
A14: Vifor OR margin | B14: =Inputs!$B$9 | C14: =Inputs!$B$9+Inputs!$C$35*(1/6) | D14: =Inputs!$B$9+Inputs!$C$35*(2/6) | E14: =Inputs!$B$9+Inputs!$C$35*(3/6) | F14: =Inputs!$B$9+Inputs!$C$35*(4/6) | G14: =Inputs!$B$9+Inputs!$C$35*(5/6) | H14: =Inputs!$B$9+Inputs!$C$35*(6/6)
A15: Vifor OR | B15: =B13*B14 | C15: =C13*C14 | D15: =D13*D14 | E15: =E13*E14 | F15: =F13*F14 | G15: =G13*G14 | H15: =H13*H14
A17: Group revenue | B17: =B5+B9+B13 | C17: =C5+C9+C13 | D17: =D5+D9+D13 | E17: =E5+E9+E13 | F17: =F5+F9+F13 | G17: =G5+G9+G13 | H17: =H5+H9+H13
A18: Segment OR (sum) | B18: =B7+B11+B15 | C18: =C7+C11+C15 | D18: =D7+D11+D15 | E18: =E7+E11+E15 | F18: =F7+F11+F15 | G18: =G7+G11+G15 | H18: =H7+H11+H15
A19: Corporate / unalloc | B19: =Inputs!$B$10 | C19: =Inputs!$B$10*(1.005^1) | D19: =Inputs!$B$10*(1.005^2) | E19: =Inputs!$B$10*(1.005^3) | F19: =Inputs!$B$10*(1.005^4) | G19: =Inputs!$B$10*(1.005^5) | H19: =Inputs!$B$10*(1.005^6)
A20: Group EBIT | B20: =B18+B19 | C20: =C18+C19 | D20: =D18+D19 | E20: =E18+E19 | F20: =F18+F19 | G20: =G18+G19 | H20: =H18+H19
A21: Group EBIT margin (memo) | B21: =B20/B17 | C21: =C20/C17 | D21: =D20/D17 | E21: =E20/E17 | F21: =F20/F17 | G21: =G20/G17 | H21: =H20/H17
A23: NOPAT = EBIT x (1-tax) | C23: =C20*(1-Inputs!$C$38) | D23: =D20*(1-Inputs!$C$38) | E23: =E20*(1-Inputs!$C$38) | F23: =F20*(1-Inputs!$C$38) | G23: =G20*(1-Inputs!$C$38) | H23: =H20*(1-Inputs!$C$38)
A24: Plus: D&A | C24: =C17*Inputs!$B$12 | D24: =D17*Inputs!$B$12 | E24: =E17*Inputs!$B$12 | F24: =F17*Inputs!$B$12 | G24: =G17*Inputs!$B$12 | H24: =H17*Inputs!$B$12
A25: Less: capex | C25: =-C17*Inputs!$B$11 | D25: =-D17*Inputs!$B$11 | E25: =-E17*Inputs!$B$11 | F25: =-F17*Inputs!$B$11 | G25: =-G17*Inputs!$B$11 | H25: =-H17*Inputs!$B$11
A26: Less: WC change | C26: =-(C17-B17)*Inputs!$B$13 | D26: =-(D17-C17)*Inputs!$B$13 | E26: =-(E17-D17)*Inputs!$B$13 | F26: =-(F17-E17)*Inputs!$B$13 | G26: =-(G17-F17)*Inputs!$B$13 | H26: =-(H17-G17)*Inputs!$B$13
A27: FCFF | C27: =C23+C24+C25+C26 | D27: =D23+D24+D25+D26 | E27: =E23+E24+E25+E26 | F27: =F23+F24+F25+F26 | G27: =G23+G24+G25+G26 | H27: =H23+H24+H25+H26
A28: Mid-period t (FY26 excl.) | C28: 0 | D28: 0.5 | E28: 1.5 | F28: 2.5 | G28: 3.5 | H28: 4.5
A29: Discount factor | C29: =1/(1+Inputs!$B$22)^C28 | D29: =1/(1+Inputs!$B$22)^D28 | E29: =1/(1+Inputs!$B$22)^E28 | F29: =1/(1+Inputs!$B$22)^F28 | G29: =1/(1+Inputs!$B$22)^G28 | H29: =1/(1+Inputs!$B$22)^H28
A30: PV of FCFF (FY27–FY31) | C30: 0 | D30: =D27*D29 | E30: =E27*E29 | F30: =F27*F29 | G30: =G27*G29 | H30: =H27*H29
A32: Sum explicit PV (FY27–FY31) | C32: =SUM(D30:H30)
A33: Terminal FCFF (FY31 normalised) | C33: =(H17*Inputs!$C$36*(1-Inputs!$C$38)+H17*Inputs!$B$12-H17*Inputs!$B$11-H17*Inputs!$C$37*Inputs!$B$13)*(1+Inputs!$C$37)
A34: Terminal value (Gordon) | C34: =C33/(Inputs!$B$22-Inputs!$C$37)
A35: Discount factor t=5 | C35: =1/(1+Inputs!$B$22)^5
A36: PV of terminal value | C36: =C34*C35
A37: Enterprise value | C37: =C32+C36
A38: Less: net debt | C38: =-Inputs!$B$17
A39: Less: restructuring cash | C39: =-Inputs!$B$18
A40: Equity value | C40: =C37+C38+C39
A41: Shares (m) | C41: =Inputs!$B$19
A42: Value per share (USD) | C42: =C40/C41
A43: Value per share (AUD) | C43: =C42*Inputs!$B$20
A44: Terminal % of EV (memo) | C44: =C36/C37

Sheet S_Muddle
A1: Muddle Through — segment DCF (USD m)
A3: Line | B3: FY25 | C3: FY26 | D3: FY27 | E3: FY28 | F3: FY29 | G3: FY30 | H3: FY31
A5: Behring revenue | B5: =Inputs!$B$3 | C5: =B5*(1+Inputs!$D$25) | D5: =C5*(1+Inputs!$D$26) | E5: =D5*(1+Inputs!$D$27) | F5: =E5*(1+Inputs!$D$28) | G5: =F5*(1+Inputs!$D$29) | H5: =G5*(1+Inputs!$D$30)
A6: Behring OR margin | B6: =Inputs!$B$7 | C6: =Inputs!$B$7+Inputs!$D$33*(1/6) | D6: =Inputs!$B$7+Inputs!$D$33*(2/6) | E6: =Inputs!$B$7+Inputs!$D$33*(3/6) | F6: =Inputs!$B$7+Inputs!$D$33*(4/6) | G6: =Inputs!$B$7+Inputs!$D$33*(5/6) | H6: =Inputs!$B$7+Inputs!$D$33*(6/6)
A7: Behring OR | B7: =B5*B6 | C7: =C5*C6 | D7: =D5*D6 | E7: =E5*E6 | F7: =F5*F6 | G7: =G5*G6 | H7: =H5*H6
A9: Seqirus revenue | B9: =Inputs!$B$4 | C9: =B9*(1+Inputs!$D$31) | D9: =C9*(1+Inputs!$D$31) | E9: =D9*(1+Inputs!$D$31) | F9: =E9*(1+Inputs!$D$31) | G9: =F9*(1+Inputs!$D$31) | H9: =G9*(1+Inputs!$D$31)
A10: Seqirus OR margin | B10: =Inputs!$B$8 | C10: =Inputs!$B$8+Inputs!$D$34*(1/6) | D10: =Inputs!$B$8+Inputs!$D$34*(2/6) | E10: =Inputs!$B$8+Inputs!$D$34*(3/6) | F10: =Inputs!$B$8+Inputs!$D$34*(4/6) | G10: =Inputs!$B$8+Inputs!$D$34*(5/6) | H10: =Inputs!$B$8+Inputs!$D$34*(6/6)
A11: Seqirus OR | B11: =B9*B10 | C11: =C9*C10 | D11: =D9*D10 | E11: =E9*E10 | F11: =F9*F10 | G11: =G9*G10 | H11: =H9*H10
A13: Vifor revenue | B13: =Inputs!$B$5 | C13: =B13*(1+Inputs!$D$32) | D13: =C13*(1+Inputs!$D$32) | E13: =D13*(1+Inputs!$D$32) | F13: =E13*(1+Inputs!$D$32) | G13: =F13*(1+Inputs!$D$32) | H13: =G13*(1+Inputs!$D$32)
A14: Vifor OR margin | B14: =Inputs!$B$9 | C14: =Inputs!$B$9+Inputs!$D$35*(1/6) | D14: =Inputs!$B$9+Inputs!$D$35*(2/6) | E14: =Inputs!$B$9+Inputs!$D$35*(3/6) | F14: =Inputs!$B$9+Inputs!$D$35*(4/6) | G14: =Inputs!$B$9+Inputs!$D$35*(5/6) | H14: =Inputs!$B$9+Inputs!$D$35*(6/6)
A15: Vifor OR | B15: =B13*B14 | C15: =C13*C14 | D15: =D13*D14 | E15: =E13*E14 | F15: =F13*F14 | G15: =G13*G14 | H15: =H13*H14
A17: Group revenue | B17: =B5+B9+B13 | C17: =C5+C9+C13 | D17: =D5+D9+D13 | E17: =E5+E9+E13 | F17: =F5+F9+F13 | G17: =G5+G9+G13 | H17: =H5+H9+H13
A18: Segment OR (sum) | B18: =B7+B11+B15 | C18: =C7+C11+C15 | D18: =D7+D11+D15 | E18: =E7+E11+E15 | F18: =F7+F11+F15 | G18: =G7+G11+G15 | H18: =H7+H11+H15
A19: Corporate / unalloc | B19: =Inputs!$B$10 | C19: =Inputs!$B$10*(1.005^1) | D19: =Inputs!$B$10*(1.005^2) | E19: =Inputs!$B$10*(1.005^3) | F19: =Inputs!$B$10*(1.005^4) | G19: =Inputs!$B$10*(1.005^5) | H19: =Inputs!$B$10*(1.005^6)
A20: Group EBIT | B20: =B18+B19 | C20: =C18+C19 | D20: =D18+D19 | E20: =E18+E19 | F20: =F18+F19 | G20: =G18+G19 | H20: =H18+H19
A21: Group EBIT margin (memo) | B21: =B20/B17 | C21: =C20/C17 | D21: =D20/D17 | E21: =E20/E17 | F21: =F20/F17 | G21: =G20/G17 | H21: =H20/H17
A23: NOPAT = EBIT x (1-tax) | C23: =C20*(1-Inputs!$D$38) | D23: =D20*(1-Inputs!$D$38) | E23: =E20*(1-Inputs!$D$38) | F23: =F20*(1-Inputs!$D$38) | G23: =G20*(1-Inputs!$D$38) | H23: =H20*(1-Inputs!$D$38)
A24: Plus: D&A | C24: =C17*Inputs!$B$12 | D24: =D17*Inputs!$B$12 | E24: =E17*Inputs!$B$12 | F24: =F17*Inputs!$B$12 | G24: =G17*Inputs!$B$12 | H24: =H17*Inputs!$B$12
A25: Less: capex | C25: =-C17*Inputs!$B$11 | D25: =-D17*Inputs!$B$11 | E25: =-E17*Inputs!$B$11 | F25: =-F17*Inputs!$B$11 | G25: =-G17*Inputs!$B$11 | H25: =-H17*Inputs!$B$11
A26: Less: WC change | C26: =-(C17-B17)*Inputs!$B$13 | D26: =-(D17-C17)*Inputs!$B$13 | E26: =-(E17-D17)*Inputs!$B$13 | F26: =-(F17-E17)*Inputs!$B$13 | G26: =-(G17-F17)*Inputs!$B$13 | H26: =-(H17-G17)*Inputs!$B$13
A27: FCFF | C27: =C23+C24+C25+C26 | D27: =D23+D24+D25+D26 | E27: =E23+E24+E25+E26 | F27: =F23+F24+F25+F26 | G27: =G23+G24+G25+G26 | H27: =H23+H24+H25+H26
A28: Mid-period t (FY26 excl.) | C28: 0 | D28: 0.5 | E28: 1.5 | F28: 2.5 | G28: 3.5 | H28: 4.5
A29: Discount factor | C29: =1/(1+Inputs!$B$22)^C28 | D29: =1/(1+Inputs!$B$22)^D28 | E29: =1/(1+Inputs!$B$22)^E28 | F29: =1/(1+Inputs!$B$22)^F28 | G29: =1/(1+Inputs!$B$22)^G28 | H29: =1/(1+Inputs!$B$22)^H28
A30: PV of FCFF (FY27–FY31) | C30: 0 | D30: =D27*D29 | E30: =E27*E29 | F30: =F27*F29 | G30: =G27*G29 | H30: =H27*H29
A32: Sum explicit PV (FY27–FY31) | C32: =SUM(D30:H30)
A33: Terminal FCFF (FY31 normalised) | C33: =(H17*Inputs!$D$36*(1-Inputs!$D$38)+H17*Inputs!$B$12-H17*Inputs!$B$11-H17*Inputs!$D$37*Inputs!$B$13)*(1+Inputs!$D$37)
A34: Terminal value (Gordon) | C34: =C33/(Inputs!$B$22-Inputs!$D$37)
A35: Discount factor t=5 | C35: =1/(1+Inputs!$B$22)^5
A36: PV of terminal value | C36: =C34*C35
A37: Enterprise value | C37: =C32+C36
A38: Less: net debt | C38: =-Inputs!$B$17
A39: Less: restructuring cash | C39: =-Inputs!$B$18
A40: Equity value | C40: =C37+C38+C39
A41: Shares (m) | C41: =Inputs!$B$19
A42: Value per share (USD) | C42: =C40/C41
A43: Value per share (AUD) | C43: =C42*Inputs!$B$20
A44: Terminal % of EV (memo) | C44: =C36/C37

Sheet S_AI
A1: AI Productivity Lag — segment DCF (USD m)
A3: Line | B3: FY25 | C3: FY26 | D3: FY27 | E3: FY28 | F3: FY29 | G3: FY30 | H3: FY31
A5: Behring revenue | B5: =Inputs!$B$3 | C5: =B5*(1+Inputs!$E$25) | D5: =C5*(1+Inputs!$E$26) | E5: =D5*(1+Inputs!$E$27) | F5: =E5*(1+Inputs!$E$28) | G5: =F5*(1+Inputs!$E$29) | H5: =G5*(1+Inputs!$E$30)
A6: Behring OR margin | B6: =Inputs!$B$7 | C6: =Inputs!$B$7+Inputs!$E$33*(1/6) | D6: =Inputs!$B$7+Inputs!$E$33*(2/6) | E6: =Inputs!$B$7+Inputs!$E$33*(3/6) | F6: =Inputs!$B$7+Inputs!$E$33*(4/6) | G6: =Inputs!$B$7+Inputs!$E$33*(5/6) | H6: =Inputs!$B$7+Inputs!$E$33*(6/6)
A7: Behring OR | B7: =B5*B6 | C7: =C5*C6 | D7: =D5*D6 | E7: =E5*E6 | F7: =F5*F6 | G7: =G5*G6 | H7: =H5*H6
A9: Seqirus revenue | B9: =Inputs!$B$4 | C9: =B9*(1+Inputs!$E$31) | D9: =C9*(1+Inputs!$E$31) | E9: =D9*(1+Inputs!$E$31) | F9: =E9*(1+Inputs!$E$31) | G9: =F9*(1+Inputs!$E$31) | H9: =G9*(1+Inputs!$E$31)
A10: Seqirus OR margin | B10: =Inputs!$B$8 | C10: =Inputs!$B$8+Inputs!$E$34*(1/6) | D10: =Inputs!$B$8+Inputs!$E$34*(2/6) | E10: =Inputs!$B$8+Inputs!$E$34*(3/6) | F10: =Inputs!$B$8+Inputs!$E$34*(4/6) | G10: =Inputs!$B$8+Inputs!$E$34*(5/6) | H10: =Inputs!$B$8+Inputs!$E$34*(6/6)
A11: Seqirus OR | B11: =B9*B10 | C11: =C9*C10 | D11: =D9*D10 | E11: =E9*E10 | F11: =F9*F10 | G11: =G9*G10 | H11: =H9*H10
A13: Vifor revenue | B13: =Inputs!$B$5 | C13: =B13*(1+Inputs!$E$32) | D13: =C13*(1+Inputs!$E$32) | E13: =D13*(1+Inputs!$E$32) | F13: =E13*(1+Inputs!$E$32) | G13: =F13*(1+Inputs!$E$32) | H13: =G13*(1+Inputs!$E$32)
A14: Vifor OR margin | B14: =Inputs!$B$9 | C14: =Inputs!$B$9+Inputs!$E$35*(1/6) | D14: =Inputs!$B$9+Inputs!$E$35*(2/6) | E14: =Inputs!$B$9+Inputs!$E$35*(3/6) | F14: =Inputs!$B$9+Inputs!$E$35*(4/6) | G14: =Inputs!$B$9+Inputs!$E$35*(5/6) | H14: =Inputs!$B$9+Inputs!$E$35*(6/6)
A15: Vifor OR | B15: =B13*B14 | C15: =C13*C14 | D15: =D13*D14 | E15: =E13*E14 | F15: =F13*F14 | G15: =G13*G14 | H15: =H13*H14
A17: Group revenue | B17: =B5+B9+B13 | C17: =C5+C9+C13 | D17: =D5+D9+D13 | E17: =E5+E9+E13 | F17: =F5+F9+F13 | G17: =G5+G9+G13 | H17: =H5+H9+H13
A18: Segment OR (sum) | B18: =B7+B11+B15 | C18: =C7+C11+C15 | D18: =D7+D11+D15 | E18: =E7+E11+E15 | F18: =F7+F11+F15 | G18: =G7+G11+G15 | H18: =H7+H11+H15
A19: Corporate / unalloc | B19: =Inputs!$B$10 | C19: =Inputs!$B$10*(1.005^1) | D19: =Inputs!$B$10*(1.005^2) | E19: =Inputs!$B$10*(1.005^3) | F19: =Inputs!$B$10*(1.005^4) | G19: =Inputs!$B$10*(1.005^5) | H19: =Inputs!$B$10*(1.005^6)
A20: Group EBIT | B20: =B18+B19 | C20: =C18+C19 | D20: =D18+D19 | E20: =E18+E19 | F20: =F18+F19 | G20: =G18+G19 | H20: =H18+H19
A21: Group EBIT margin (memo) | B21: =B20/B17 | C21: =C20/C17 | D21: =D20/D17 | E21: =E20/E17 | F21: =F20/F17 | G21: =G20/G17 | H21: =H20/H17
A23: NOPAT = EBIT x (1-tax) | C23: =C20*(1-Inputs!$E$38) | D23: =D20*(1-Inputs!$E$38) | E23: =E20*(1-Inputs!$E$38) | F23: =F20*(1-Inputs!$E$38) | G23: =G20*(1-Inputs!$E$38) | H23: =H20*(1-Inputs!$E$38)
A24: Plus: D&A | C24: =C17*Inputs!$B$12 | D24: =D17*Inputs!$B$12 | E24: =E17*Inputs!$B$12 | F24: =F17*Inputs!$B$12 | G24: =G17*Inputs!$B$12 | H24: =H17*Inputs!$B$12
A25: Less: capex | C25: =-C17*Inputs!$B$11 | D25: =-D17*Inputs!$B$11 | E25: =-E17*Inputs!$B$11 | F25: =-F17*Inputs!$B$11 | G25: =-G17*Inputs!$B$11 | H25: =-H17*Inputs!$B$11
A26: Less: WC change | C26: =-(C17-B17)*Inputs!$B$13 | D26: =-(D17-C17)*Inputs!$B$13 | E26: =-(E17-D17)*Inputs!$B$13 | F26: =-(F17-E17)*Inputs!$B$13 | G26: =-(G17-F17)*Inputs!$B$13 | H26: =-(H17-G17)*Inputs!$B$13
A27: FCFF | C27: =C23+C24+C25+C26 | D27: =D23+D24+D25+D26 | E27: =E23+E24+E25+E26 | F27: =F23+F24+F25+F26 | G27: =G23+G24+G25+G26 | H27: =H23+H24+H25+H26
A28: Mid-period t (FY26 excl.) | C28: 0 | D28: 0.5 | E28: 1.5 | F28: 2.5 | G28: 3.5 | H28: 4.5
A29: Discount factor | C29: =1/(1+Inputs!$B$22)^C28 | D29: =1/(1+Inputs!$B$22)^D28 | E29: =1/(1+Inputs!$B$22)^E28 | F29: =1/(1+Inputs!$B$22)^F28 | G29: =1/(1+Inputs!$B$22)^G28 | H29: =1/(1+Inputs!$B$22)^H28
A30: PV of FCFF (FY27–FY31) | C30: 0 | D30: =D27*D29 | E30: =E27*E29 | F30: =F27*F29 | G30: =G27*G29 | H30: =H27*H29
A32: Sum explicit PV (FY27–FY31) | C32: =SUM(D30:H30)
A33: Terminal FCFF (FY31 normalised) | C33: =(H17*Inputs!$E$36*(1-Inputs!$E$38)+H17*Inputs!$B$12-H17*Inputs!$B$11-H17*Inputs!$E$37*Inputs!$B$13)*(1+Inputs!$E$37)
A34: Terminal value (Gordon) | C34: =C33/(Inputs!$B$22-Inputs!$E$37)
A35: Discount factor t=5 | C35: =1/(1+Inputs!$B$22)^5
A36: PV of terminal value | C36: =C34*C35
A37: Enterprise value | C37: =C32+C36
A38: Less: net debt | C38: =-Inputs!$B$17
A39: Less: restructuring cash | C39: =-Inputs!$B$18
A40: Equity value | C40: =C37+C38+C39
A41: Shares (m) | C41: =Inputs!$B$19
A42: Value per share (USD) | C42: =C40/C41
A43: Value per share (AUD) | C43: =C42*Inputs!$B$20
A44: Terminal % of EV (memo) | C44: =C36/C37

Sheet S_Disorderly
A1: Disorderly Climate — segment DCF (USD m)
A3: Line | B3: FY25 | C3: FY26 | D3: FY27 | E3: FY28 | F3: FY29 | G3: FY30 | H3: FY31
A5: Behring revenue | B5: =Inputs!$B$3 | C5: =B5*(1+Inputs!$F$25) | D5: =C5*(1+Inputs!$F$26) | E5: =D5*(1+Inputs!$F$27) | F5: =E5*(1+Inputs!$F$28) | G5: =F5*(1+Inputs!$F$29) | H5: =G5*(1+Inputs!$F$30)
A6: Behring OR margin | B6: =Inputs!$B$7 | C6: =Inputs!$B$7+Inputs!$F$33*(1/6) | D6: =Inputs!$B$7+Inputs!$F$33*(2/6) | E6: =Inputs!$B$7+Inputs!$F$33*(3/6) | F6: =Inputs!$B$7+Inputs!$F$33*(4/6) | G6: =Inputs!$B$7+Inputs!$F$33*(5/6) | H6: =Inputs!$B$7+Inputs!$F$33*(6/6)
A7: Behring OR | B7: =B5*B6 | C7: =C5*C6 | D7: =D5*D6 | E7: =E5*E6 | F7: =F5*F6 | G7: =G5*G6 | H7: =H5*H6
A9: Seqirus revenue | B9: =Inputs!$B$4 | C9: =B9*(1+Inputs!$F$31) | D9: =C9*(1+Inputs!$F$31) | E9: =D9*(1+Inputs!$F$31) | F9: =E9*(1+Inputs!$F$31) | G9: =F9*(1+Inputs!$F$31) | H9: =G9*(1+Inputs!$F$31)
A10: Seqirus OR margin | B10: =Inputs!$B$8 | C10: =Inputs!$B$8+Inputs!$F$34*(1/6) | D10: =Inputs!$B$8+Inputs!$F$34*(2/6) | E10: =Inputs!$B$8+Inputs!$F$34*(3/6) | F10: =Inputs!$B$8+Inputs!$F$34*(4/6) | G10: =Inputs!$B$8+Inputs!$F$34*(5/6) | H10: =Inputs!$B$8+Inputs!$F$34*(6/6)
A11: Seqirus OR | B11: =B9*B10 | C11: =C9*C10 | D11: =D9*D10 | E11: =E9*E10 | F11: =F9*F10 | G11: =G9*G10 | H11: =H9*H10
A13: Vifor revenue | B13: =Inputs!$B$5 | C13: =B13*(1+Inputs!$F$32) | D13: =C13*(1+Inputs!$F$32) | E13: =D13*(1+Inputs!$F$32) | F13: =E13*(1+Inputs!$F$32) | G13: =F13*(1+Inputs!$F$32) | H13: =G13*(1+Inputs!$F$32)
A14: Vifor OR margin | B14: =Inputs!$B$9 | C14: =Inputs!$B$9+Inputs!$F$35*(1/6) | D14: =Inputs!$B$9+Inputs!$F$35*(2/6) | E14: =Inputs!$B$9+Inputs!$F$35*(3/6) | F14: =Inputs!$B$9+Inputs!$F$35*(4/6) | G14: =Inputs!$B$9+Inputs!$F$35*(5/6) | H14: =Inputs!$B$9+Inputs!$F$35*(6/6)
A15: Vifor OR | B15: =B13*B14 | C15: =C13*C14 | D15: =D13*D14 | E15: =E13*E14 | F15: =F13*F14 | G15: =G13*G14 | H15: =H13*H14
A17: Group revenue | B17: =B5+B9+B13 | C17: =C5+C9+C13 | D17: =D5+D9+D13 | E17: =E5+E9+E13 | F17: =F5+F9+F13 | G17: =G5+G9+G13 | H17: =H5+H9+H13
A18: Segment OR (sum) | B18: =B7+B11+B15 | C18: =C7+C11+C15 | D18: =D7+D11+D15 | E18: =E7+E11+E15 | F18: =F7+F11+F15 | G18: =G7+G11+G15 | H18: =H7+H11+H15
A19: Corporate / unalloc | B19: =Inputs!$B$10 | C19: =Inputs!$B$10*(1.005^1) | D19: =Inputs!$B$10*(1.005^2) | E19: =Inputs!$B$10*(1.005^3) | F19: =Inputs!$B$10*(1.005^4) | G19: =Inputs!$B$10*(1.005^5) | H19: =Inputs!$B$10*(1.005^6)
A20: Group EBIT | B20: =B18+B19 | C20: =C18+C19 | D20: =D18+D19 | E20: =E18+E19 | F20: =F18+F19 | G20: =G18+G19 | H20: =H18+H19
A21: Group EBIT margin (memo) | B21: =B20/B17 | C21: =C20/C17 | D21: =D20/D17 | E21: =E20/E17 | F21: =F20/F17 | G21: =G20/G17 | H21: =H20/H17
A23: NOPAT = EBIT x (1-tax) | C23: =C20*(1-Inputs!$F$38) | D23: =D20*(1-Inputs!$F$38) | E23: =E20*(1-Inputs!$F$38) | F23: =F20*(1-Inputs!$F$38) | G23: =G20*(1-Inputs!$F$38) | H23: =H20*(1-Inputs!$F$38)
A24: Plus: D&A | C24: =C17*Inputs!$B$12 | D24: =D17*Inputs!$B$12 | E24: =E17*Inputs!$B$12 | F24: =F17*Inputs!$B$12 | G24: =G17*Inputs!$B$12 | H24: =H17*Inputs!$B$12
A25: Less: capex | C25: =-C17*Inputs!$B$11 | D25: =-D17*Inputs!$B$11 | E25: =-E17*Inputs!$B$11 | F25: =-F17*Inputs!$B$11 | G25: =-G17*Inputs!$B$11 | H25: =-H17*Inputs!$B$11
A26: Less: WC change | C26: =-(C17-B17)*Inputs!$B$13 | D26: =-(D17-C17)*Inputs!$B$13 | E26: =-(E17-D17)*Inputs!$B$13 | F26: =-(F17-E17)*Inputs!$B$13 | G26: =-(G17-F17)*Inputs!$B$13 | H26: =-(H17-G17)*Inputs!$B$13
A27: FCFF | C27: =C23+C24+C25+C26 | D27: =D23+D24+D25+D26 | E27: =E23+E24+E25+E26 | F27: =F23+F24+F25+F26 | G27: =G23+G24+G25+G26 | H27: =H23+H24+H25+H26
A28: Mid-period t (FY26 excl.) | C28: 0 | D28: 0.5 | E28: 1.5 | F28: 2.5 | G28: 3.5 | H28: 4.5
A29: Discount factor | C29: =1/(1+Inputs!$B$22)^C28 | D29: =1/(1+Inputs!$B$22)^D28 | E29: =1/(1+Inputs!$B$22)^E28 | F29: =1/(1+Inputs!$B$22)^F28 | G29: =1/(1+Inputs!$B$22)^G28 | H29: =1/(1+Inputs!$B$22)^H28
A30: PV of FCFF (FY27–FY31) | C30: 0 | D30: =D27*D29 | E30: =E27*E29 | F30: =F27*F29 | G30: =G27*G29 | H30: =H27*H29
A32: Sum explicit PV (FY27–FY31) | C32: =SUM(D30:H30)
A33: Terminal FCFF (FY31 normalised) | C33: =(H17*Inputs!$F$36*(1-Inputs!$F$38)+H17*Inputs!$B$12-H17*Inputs!$B$11-H17*Inputs!$F$37*Inputs!$B$13)*(1+Inputs!$F$37)
A34: Terminal value (Gordon) | C34: =C33/(Inputs!$B$22-Inputs!$F$37)
A35: Discount factor t=5 | C35: =1/(1+Inputs!$B$22)^5
A36: PV of terminal value | C36: =C34*C35
A37: Enterprise value | C37: =C32+C36
A38: Less: net debt | C38: =-Inputs!$B$17
A39: Less: restructuring cash | C39: =-Inputs!$B$18
A40: Equity value | C40: =C37+C38+C39
A41: Shares (m) | C41: =Inputs!$B$19
A42: Value per share (USD) | C42: =C40/C41
A43: Value per share (AUD) | C43: =C42*Inputs!$B$20
A44: Terminal % of EV (memo) | C44: =C36/C37

Sheet S_Fragmentation
A1: Fragmentation — segment DCF (USD m)
A3: Line | B3: FY25 | C3: FY26 | D3: FY27 | E3: FY28 | F3: FY29 | G3: FY30 | H3: FY31
A5: Behring revenue | B5: =Inputs!$B$3 | C5: =B5*(1+Inputs!$G$25) | D5: =C5*(1+Inputs!$G$26) | E5: =D5*(1+Inputs!$G$27) | F5: =E5*(1+Inputs!$G$28) | G5: =F5*(1+Inputs!$G$29) | H5: =G5*(1+Inputs!$G$30)
A6: Behring OR margin | B6: =Inputs!$B$7 | C6: =Inputs!$B$7+Inputs!$G$33*(1/6) | D6: =Inputs!$B$7+Inputs!$G$33*(2/6) | E6: =Inputs!$B$7+Inputs!$G$33*(3/6) | F6: =Inputs!$B$7+Inputs!$G$33*(4/6) | G6: =Inputs!$B$7+Inputs!$G$33*(5/6) | H6: =Inputs!$B$7+Inputs!$G$33*(6/6)
A7: Behring OR | B7: =B5*B6 | C7: =C5*C6 | D7: =D5*D6 | E7: =E5*E6 | F7: =F5*F6 | G7: =G5*G6 | H7: =H5*H6
A9: Seqirus revenue | B9: =Inputs!$B$4 | C9: =B9*(1+Inputs!$G$31) | D9: =C9*(1+Inputs!$G$31) | E9: =D9*(1+Inputs!$G$31) | F9: =E9*(1+Inputs!$G$31) | G9: =F9*(1+Inputs!$G$31) | H9: =G9*(1+Inputs!$G$31)
A10: Seqirus OR margin | B10: =Inputs!$B$8 | C10: =Inputs!$B$8+Inputs!$G$34*(1/6) | D10: =Inputs!$B$8+Inputs!$G$34*(2/6) | E10: =Inputs!$B$8+Inputs!$G$34*(3/6) | F10: =Inputs!$B$8+Inputs!$G$34*(4/6) | G10: =Inputs!$B$8+Inputs!$G$34*(5/6) | H10: =Inputs!$B$8+Inputs!$G$34*(6/6)
A11: Seqirus OR | B11: =B9*B10 | C11: =C9*C10 | D11: =D9*D10 | E11: =E9*E10 | F11: =F9*F10 | G11: =G9*G10 | H11: =H9*H10
A13: Vifor revenue | B13: =Inputs!$B$5 | C13: =B13*(1+Inputs!$G$32) | D13: =C13*(1+Inputs!$G$32) | E13: =D13*(1+Inputs!$G$32) | F13: =E13*(1+Inputs!$G$32) | G13: =F13*(1+Inputs!$G$32) | H13: =G13*(1+Inputs!$G$32)
A14: Vifor OR margin | B14: =Inputs!$B$9 | C14: =Inputs!$B$9+Inputs!$G$35*(1/6) | D14: =Inputs!$B$9+Inputs!$G$35*(2/6) | E14: =Inputs!$B$9+Inputs!$G$35*(3/6) | F14: =Inputs!$B$9+Inputs!$G$35*(4/6) | G14: =Inputs!$B$9+Inputs!$G$35*(5/6) | H14: =Inputs!$B$9+Inputs!$G$35*(6/6)
A15: Vifor OR | B15: =B13*B14 | C15: =C13*C14 | D15: =D13*D14 | E15: =E13*E14 | F15: =F13*F14 | G15: =G13*G14 | H15: =H13*H14
A17: Group revenue | B17: =B5+B9+B13 | C17: =C5+C9+C13 | D17: =D5+D9+D13 | E17: =E5+E9+E13 | F17: =F5+F9+F13 | G17: =G5+G9+G13 | H17: =H5+H9+H13
A18: Segment OR (sum) | B18: =B7+B11+B15 | C18: =C7+C11+C15 | D18: =D7+D11+D15 | E18: =E7+E11+E15 | F18: =F7+F11+F15 | G18: =G7+G11+G15 | H18: =H7+H11+H15
A19: Corporate / unalloc | B19: =Inputs!$B$10 | C19: =Inputs!$B$10*(1.005^1) | D19: =Inputs!$B$10*(1.005^2) | E19: =Inputs!$B$10*(1.005^3) | F19: =Inputs!$B$10*(1.005^4) | G19: =Inputs!$B$10*(1.005^5) | H19: =Inputs!$B$10*(1.005^6)
A20: Group EBIT | B20: =B18+B19 | C20: =C18+C19 | D20: =D18+D19 | E20: =E18+E19 | F20: =F18+F19 | G20: =G18+G19 | H20: =H18+H19
A21: Group EBIT margin (memo) | B21: =B20/B17 | C21: =C20/C17 | D21: =D20/D17 | E21: =E20/E17 | F21: =F20/F17 | G21: =G20/G17 | H21: =H20/H17
A23: NOPAT = EBIT x (1-tax) | C23: =C20*(1-Inputs!$G$38) | D23: =D20*(1-Inputs!$G$38) | E23: =E20*(1-Inputs!$G$38) | F23: =F20*(1-Inputs!$G$38) | G23: =G20*(1-Inputs!$G$38) | H23: =H20*(1-Inputs!$G$38)
A24: Plus: D&A | C24: =C17*Inputs!$B$12 | D24: =D17*Inputs!$B$12 | E24: =E17*Inputs!$B$12 | F24: =F17*Inputs!$B$12 | G24: =G17*Inputs!$B$12 | H24: =H17*Inputs!$B$12
A25: Less: capex | C25: =-C17*Inputs!$B$11 | D25: =-D17*Inputs!$B$11 | E25: =-E17*Inputs!$B$11 | F25: =-F17*Inputs!$B$11 | G25: =-G17*Inputs!$B$11 | H25: =-H17*Inputs!$B$11
A26: Less: WC change | C26: =-(C17-B17)*Inputs!$B$13 | D26: =-(D17-C17)*Inputs!$B$13 | E26: =-(E17-D17)*Inputs!$B$13 | F26: =-(F17-E17)*Inputs!$B$13 | G26: =-(G17-F17)*Inputs!$B$13 | H26: =-(H17-G17)*Inputs!$B$13
A27: FCFF | C27: =C23+C24+C25+C26 | D27: =D23+D24+D25+D26 | E27: =E23+E24+E25+E26 | F27: =F23+F24+F25+F26 | G27: =G23+G24+G25+G26 | H27: =H23+H24+H25+H26
A28: Mid-period t (FY26 excl.) | C28: 0 | D28: 0.5 | E28: 1.5 | F28: 2.5 | G28: 3.5 | H28: 4.5
A29: Discount factor | C29: =1/(1+Inputs!$B$22)^C28 | D29: =1/(1+Inputs!$B$22)^D28 | E29: =1/(1+Inputs!$B$22)^E28 | F29: =1/(1+Inputs!$B$22)^F28 | G29: =1/(1+Inputs!$B$22)^G28 | H29: =1/(1+Inputs!$B$22)^H28
A30: PV of FCFF (FY27–FY31) | C30: 0 | D30: =D27*D29 | E30: =E27*E29 | F30: =F27*F29 | G30: =G27*G29 | H30: =H27*H29
A32: Sum explicit PV (FY27–FY31) | C32: =SUM(D30:H30)
A33: Terminal FCFF (FY31 normalised) | C33: =(H17*Inputs!$G$36*(1-Inputs!$G$38)+H17*Inputs!$B$12-H17*Inputs!$B$11-H17*Inputs!$G$37*Inputs!$B$13)*(1+Inputs!$G$37)
A34: Terminal value (Gordon) | C34: =C33/(Inputs!$B$22-Inputs!$G$37)
A35: Discount factor t=5 | C35: =1/(1+Inputs!$B$22)^5
A36: PV of terminal value | C36: =C34*C35
A37: Enterprise value | C37: =C32+C36
A38: Less: net debt | C38: =-Inputs!$B$17
A39: Less: restructuring cash | C39: =-Inputs!$B$18
A40: Equity value | C40: =C37+C38+C39
A41: Shares (m) | C41: =Inputs!$B$19
A42: Value per share (USD) | C42: =C40/C41
A43: Value per share (AUD) | C43: =C42*Inputs!$B$20
A44: Terminal % of EV (memo) | C44: =C36/C37

Sheet S_Stagflation
A1: Stagflation Persists — segment DCF (USD m)
A3: Line | B3: FY25 | C3: FY26 | D3: FY27 | E3: FY28 | F3: FY29 | G3: FY30 | H3: FY31
A5: Behring revenue | B5: =Inputs!$B$3 | C5: =B5*(1+Inputs!$H$25) | D5: =C5*(1+Inputs!$H$26) | E5: =D5*(1+Inputs!$H$27) | F5: =E5*(1+Inputs!$H$28) | G5: =F5*(1+Inputs!$H$29) | H5: =G5*(1+Inputs!$H$30)
A6: Behring OR margin | B6: =Inputs!$B$7 | C6: =Inputs!$B$7+Inputs!$H$33*(1/6) | D6: =Inputs!$B$7+Inputs!$H$33*(2/6) | E6: =Inputs!$B$7+Inputs!$H$33*(3/6) | F6: =Inputs!$B$7+Inputs!$H$33*(4/6) | G6: =Inputs!$B$7+Inputs!$H$33*(5/6) | H6: =Inputs!$B$7+Inputs!$H$33*(6/6)
A7: Behring OR | B7: =B5*B6 | C7: =C5*C6 | D7: =D5*D6 | E7: =E5*E6 | F7: =F5*F6 | G7: =G5*G6 | H7: =H5*H6
A9: Seqirus revenue | B9: =Inputs!$B$4 | C9: =B9*(1+Inputs!$H$31) | D9: =C9*(1+Inputs!$H$31) | E9: =D9*(1+Inputs!$H$31) | F9: =E9*(1+Inputs!$H$31) | G9: =F9*(1+Inputs!$H$31) | H9: =G9*(1+Inputs!$H$31)
A10: Seqirus OR margin | B10: =Inputs!$B$8 | C10: =Inputs!$B$8+Inputs!$H$34*(1/6) | D10: =Inputs!$B$8+Inputs!$H$34*(2/6) | E10: =Inputs!$B$8+Inputs!$H$34*(3/6) | F10: =Inputs!$B$8+Inputs!$H$34*(4/6) | G10: =Inputs!$B$8+Inputs!$H$34*(5/6) | H10: =Inputs!$B$8+Inputs!$H$34*(6/6)
A11: Seqirus OR | B11: =B9*B10 | C11: =C9*C10 | D11: =D9*D10 | E11: =E9*E10 | F11: =F9*F10 | G11: =G9*G10 | H11: =H9*H10
A13: Vifor revenue | B13: =Inputs!$B$5 | C13: =B13*(1+Inputs!$H$32) | D13: =C13*(1+Inputs!$H$32) | E13: =D13*(1+Inputs!$H$32) | F13: =E13*(1+Inputs!$H$32) | G13: =F13*(1+Inputs!$H$32) | H13: =G13*(1+Inputs!$H$32)
A14: Vifor OR margin | B14: =Inputs!$B$9 | C14: =Inputs!$B$9+Inputs!$H$35*(1/6) | D14: =Inputs!$B$9+Inputs!$H$35*(2/6) | E14: =Inputs!$B$9+Inputs!$H$35*(3/6) | F14: =Inputs!$B$9+Inputs!$H$35*(4/6) | G14: =Inputs!$B$9+Inputs!$H$35*(5/6) | H14: =Inputs!$B$9+Inputs!$H$35*(6/6)
A15: Vifor OR | B15: =B13*B14 | C15: =C13*C14 | D15: =D13*D14 | E15: =E13*E14 | F15: =F13*F14 | G15: =G13*G14 | H15: =H13*H14
A17: Group revenue | B17: =B5+B9+B13 | C17: =C5+C9+C13 | D17: =D5+D9+D13 | E17: =E5+E9+E13 | F17: =F5+F9+F13 | G17: =G5+G9+G13 | H17: =H5+H9+H13
A18: Segment OR (sum) | B18: =B7+B11+B15 | C18: =C7+C11+C15 | D18: =D7+D11+D15 | E18: =E7+E11+E15 | F18: =F7+F11+F15 | G18: =G7+G11+G15 | H18: =H7+H11+H15
A19: Corporate / unalloc | B19: =Inputs!$B$10 | C19: =Inputs!$B$10*(1.005^1) | D19: =Inputs!$B$10*(1.005^2) | E19: =Inputs!$B$10*(1.005^3) | F19: =Inputs!$B$10*(1.005^4) | G19: =Inputs!$B$10*(1.005^5) | H19: =Inputs!$B$10*(1.005^6)
A20: Group EBIT | B20: =B18+B19 | C20: =C18+C19 | D20: =D18+D19 | E20: =E18+E19 | F20: =F18+F19 | G20: =G18+G19 | H20: =H18+H19
A21: Group EBIT margin (memo) | B21: =B20/B17 | C21: =C20/C17 | D21: =D20/D17 | E21: =E20/E17 | F21: =F20/F17 | G21: =G20/G17 | H21: =H20/H17
A23: NOPAT = EBIT x (1-tax) | C23: =C20*(1-Inputs!$H$38) | D23: =D20*(1-Inputs!$H$38) | E23: =E20*(1-Inputs!$H$38) | F23: =F20*(1-Inputs!$H$38) | G23: =G20*(1-Inputs!$H$38) | H23: =H20*(1-Inputs!$H$38)
A24: Plus: D&A | C24: =C17*Inputs!$B$12 | D24: =D17*Inputs!$B$12 | E24: =E17*Inputs!$B$12 | F24: =F17*Inputs!$B$12 | G24: =G17*Inputs!$B$12 | H24: =H17*Inputs!$B$12
A25: Less: capex | C25: =-C17*Inputs!$B$11 | D25: =-D17*Inputs!$B$11 | E25: =-E17*Inputs!$B$11 | F25: =-F17*Inputs!$B$11 | G25: =-G17*Inputs!$B$11 | H25: =-H17*Inputs!$B$11
A26: Less: WC change | C26: =-(C17-B17)*Inputs!$B$13 | D26: =-(D17-C17)*Inputs!$B$13 | E26: =-(E17-D17)*Inputs!$B$13 | F26: =-(F17-E17)*Inputs!$B$13 | G26: =-(G17-F17)*Inputs!$B$13 | H26: =-(H17-G17)*Inputs!$B$13
A27: FCFF | C27: =C23+C24+C25+C26 | D27: =D23+D24+D25+D26 | E27: =E23+E24+E25+E26 | F27: =F23+F24+F25+F26 | G27: =G23+G24+G25+G26 | H27: =H23+H24+H25+H26
A28: Mid-period t (FY26 excl.) | C28: 0 | D28: 0.5 | E28: 1.5 | F28: 2.5 | G28: 3.5 | H28: 4.5
A29: Discount factor | C29: =1/(1+Inputs!$B$22)^C28 | D29: =1/(1+Inputs!$B$22)^D28 | E29: =1/(1+Inputs!$B$22)^E28 | F29: =1/(1+Inputs!$B$22)^F28 | G29: =1/(1+Inputs!$B$22)^G28 | H29: =1/(1+Inputs!$B$22)^H28
A30: PV of FCFF (FY27–FY31) | C30: 0 | D30: =D27*D29 | E30: =E27*E29 | F30: =F27*F29 | G30: =G27*G29 | H30: =H27*H29
A32: Sum explicit PV (FY27–FY31) | C32: =SUM(D30:H30)
A33: Terminal FCFF (FY31 normalised) | C33: =(H17*Inputs!$H$36*(1-Inputs!$H$38)+H17*Inputs!$B$12-H17*Inputs!$B$11-H17*Inputs!$H$37*Inputs!$B$13)*(1+Inputs!$H$37)
A34: Terminal value (Gordon) | C34: =C33/(Inputs!$B$22-Inputs!$H$37)
A35: Discount factor t=5 | C35: =1/(1+Inputs!$B$22)^5
A36: PV of terminal value | C36: =C34*C35
A37: Enterprise value | C37: =C32+C36
A38: Less: net debt | C38: =-Inputs!$B$17
A39: Less: restructuring cash | C39: =-Inputs!$B$18
A40: Equity value | C40: =C37+C38+C39
A41: Shares (m) | C41: =Inputs!$B$19
A42: Value per share (USD) | C42: =C40/C41
A43: Value per share (AUD) | C43: =C42*Inputs!$B$20
A44: Terminal % of EV (memo) | C44: =C36/C37

Sheet Notes
A1: Methodology notes
A3: Engine. Each scenario tab replicates the v3 Muddle Through segment DCF (Behring J-curve + Seqirus/Vifor CAGR; linear OR-margin glide to FY31; corporate +0.5%/yr; FCFF = NOPAT + D&A − capex − ΔWC; explicit FY27–FY31 mid-period discounted; Gordon terminal off FY31). The Muddle Through tab reproduces v3 exactly: USD 141.78 / AUD 214.82.
A4: Base. All scenarios anchor off v3 (terminal-margin fix now binding; Behring J-curve FY26 −1% → 5.5%; Behring peer-gap uplift +150bps in MT, full +250bps reserved for Orderly Convergence). Shared base inputs (segment FY25, capex/D&A/WC, Re components, net debt, restructuring, shares, FX) are identical across scenarios on the Inputs tab.
A5: Per-scenario drivers (Inputs tab, yellow). Behring 6-year growth path, Seqirus & Vifor CAGR, the three segment margin uplifts, terminal EBIT margin, terminal growth g, and effective tax. These are the only levers that move between scenarios; everything else links by formula.
A6: Calibration logic (CSL is defensive — scenarios act on margins/policy, not volumes):
A7: Orderly Convergence: benign macro, collection-cost inflation eases → full +250bps Behring closure, faster J-curve recovery, terminal margin 31.5%, g 3.25%.
A8: AI Productivity Lag: white-collar wage containment a mild margin tailwind; slightly softer macro growth and lower terminal g (2.875%). Lands marginally below MT.
A9: Disorderly Climate: carbon-cost pass-through compresses energy-intensive fractionation / cold-chain margins; Seqirus vaccine demand a partial offset. Terminal margin 28%, g 2.75%.
A10: Fragmentation: China Ig access + supply-chain localisation friction; peer-gap closure stalls (uplift 0), effective tax 20%. Terminal margin 28.2%, g 2.75%.
A11: Stagflation Persists: worst margin case — US donor-collection wage inflation + payor pricing pressure; closure reverses (Behring −150bps). Terminal margin 26.5%, g held 3% (nominal).
A12: Single-WACC discipline. Re = 8.75% held across all scenarios; terminal g is scenario-conditional (structural state), Re is not (today's marginal-investor return). Per CLAUDE.md cross-cutting conventions and methodology §3.5.
A13: Status. Calibration draft for Stephen's sign-off (25 June 2026). Thesis + discussion document deferred to the next pass per the agreed scope.
