Workbook

Sheet Cover
B1: Dyno Nobel Limited (DNL.AU) — Muddle Through valuation
B3: Scenario: | C3: Muddle Through (interior, most-likely case per Phase 3 scenarios workshop)
B4: As at: | C4: 24 May 2026 (calibration pass)
B5: Reporting currency: | C5: AUD millions unless noted
B6: Fiscal year-end: | C6: 30 September
B7: Engine: | C7: Phase 3.5 smoke-test FCF DCF (5-yr explicit + Gordon-growth terminal)
B9: Tabs:
B10: Assumptions | C10: Every input, value, source pointer and rationale. Single source of truth.
B11: P&L Summary | C11: Historicals (FY2024 combined, FY2025, TTM Mar 2026) + 5-year forecast.
B12: Balance Sheet | C12: At 30 Sep 2025 (reported) + normalised steady-state anchors.
B13: WACC Build | C13: Component build (Rf + beta x ERP, Rd, weights -> WACC). Live formulas.
B14: DCF Worksheet | C14: Year-by-year FCF, discount factors, terminal value, EV, equity, per share.
B16: Source data:
B17: Reported financials | C17: data/financials/dnl.yaml (EODHD fundamentals, Ben's data workstream, 22 May 2026)
B18: Normalised baseline | C18: data/financials/dnl.yaml normalised_baseline block (Phase 3.5 calibration, 24 May 2026)
B19: Impact matrix | C19: data/impact_matrix/by_industry/industrial_explosives.yaml (muddle_through entry)
B20: Scenario narrative | C20: data/scenarios/muddle_through.{yaml,md}
B21: Engine code | C21: src/vcc_valuations/dcf/fcf_stub.py + scripts/run_smoke_test.py
B22: Findings doc | C22: docs/phase_3_5_findings.md (Calibration pass section)
B24: Colour key:
B25: Blue text | C25: Hardcoded input — override here to flow through the model.
B26: Black text | C26: Formula / calculation.
B27: Green text | C27: Cross-sheet link.
B28: Yellow background | C28: Key assumption — flagged for attention.
B30: Smoke-test reference output: | C30: Muddle Through per share: AUD 2.53; EV AUD 6,042m; equity AUD 4,742m
B31: Market reference (21 May 2026): | C31: Share price AUD 3.61; consensus target AUD 3.61; EV AUD 7,682m

Sheet Assumptions
A1: Parameter | B1: Value | C1: Units | D1: Source / rationale
A2: BASE-YEAR FINANCIAL ANCHORS (TTM Mar 2026, normalised where flagged)
A3: Base-year revenue | B3: 3905.4 | C3: AUD m | D3: Source: TTM Mar 2026 reported revenue per data/financials/dnl.yaml income_statement.ttm_to_2026_03_31.revenue. First full 12 months post-demerger.
A4: Normalised EBIT margin | B4: 0.135 | C4: % | D4: Override. TTM reported 11.23% is depressed by post-demerger transition costs; normalised to mid-point of pre-demerger Dyno Nobel segment range (13-15%). Source: data/financials/dnl.yaml normalised_baseline.ebit_margin + rationale block.
A5: Capex / revenue (steady state) | B5: 0.07 | C5: % | D5: Override. FY25 reported 12.8% inflated by partial-year + capital restructuring. Pre-demerger normalised 6-7%. Source: normalised_baseline.capex_pct_revenue.
A6: D&A / revenue | B6: 0.073 | C6: % | D6: Roughly matches capex/revenue (steady state assumption). FY25 actual 284.1/3,710 = 7.66%. Source: normalised_baseline.da_pct_revenue.
A7: Tax rate (statutory) | B7: 0.3 | C7: % | D7: Australian statutory rate. Effective rate (FY25: 20.4%) runs lower due to franking / R&D / foreign tax credits but those are timing/mix effects. Source: normalised_baseline.tax_rate.
A8: Working-capital change | B8: 0 | C8: AUD m / yr | D8: Smoke-test simplification: assumed neutral. Production Step 7 will compute from working_capital_days x revenue growth.
A9: Net debt (reported) | B9: 1809.8 | C9: AUD m | D9: At 30 Sep 2025. Source: data/financials/dnl.yaml derived_metrics.net_debt. Inflated by post-demerger balance-sheet restructuring.
A10: Net debt (steady-state, normalised) | B10: 1300 | C10: AUD m | D10: Override. Mid-point of estimated AUD 1.2-1.4bn underlying leverage. Used in DCF for equity bridge. Source: normalised_baseline.net_debt.
A11: Shares outstanding | B11: 1875.91 | C11: m | D11: Source: data/financials/dnl.yaml share_statistics.shares_outstanding (1,875,912,826).
A13: REVENUE-GROWTH PATH (Muddle Through)
A14: Baseline nominal growth rate | B14: 0.02 | C14: % per yr | D14: GDP-adjacent nominal growth for a mature industrial in developed markets. Source: scripts/run_smoke_test.py via fcf_stub.run_fcf_dcf nominal_baseline_growth_pct.
A15: Volume-growth delta | B15: 0 | C15: % per yr | D15: Muddle Through: direction=neutral, magnitude=small -> delta 0.0% per impact-matrix translation rules (VOLUME_DELTA_PCT). Rationale: 'mining-customer capex cycle continues at current pace; demand growth tracks slow grind of global mining volumes'.
A16: Price/mix delta | B16: 0 | C16: % per yr | D16: Muddle Through: driver not populated in impact matrix (treated as neutral/small). Pass-through dynamics steady — see input_cost_pass_through entry.
A18: EBIT-MARGIN ADJUSTMENTS (Muddle Through)
A19: Gross-margin delta | B19: 0 | C19: pp | D19: Muddle Through: driver not populated (neutral). No pressure on cost structure.
A20: Input-cost pass-through delta | B20: 0 | C20: pp | D20: Muddle Through: direction=neutral, magnitude=small -> delta 0.0pp. Rationale: 'long-term gas and ammonia contracts plus established customer relationships maintain established pass-through dynamics'.
A21: SG&A pct revenue delta | B21: 0 | C21: pp | D21: Muddle Through: driver not populated (neutral). Cost base steady.
A23: WACC COMPONENT BUILD-UP
A24: Risk-free rate (Rf) | B24: 0.043 | C24: % | D24: 10-year Commonwealth of Australia government bond yield, indicative May 2026. RBA cash rate ~3.85%; 10-yr ~45bps above policy in easing cycle. Source: normalised_baseline.wacc_build.risk_free_rate.
A25: Equity risk premium (ERP) | B25: 0.05 | C25: % | D25: Damodaran-style mature-Australia ERP. Between implied global-mature mid-point (~4.6%) and Australian historical (~5.5%). Includes modest country-risk premium over US base (~50bps). Source: normalised_baseline.wacc_build.equity_risk_premium.
A26: Beta | B26: 1.15 | C26: unitless | D26: Pre-demerger IPL observed beta vs ASX200 was 1.05-1.10. Demerger leaves pure-play mining-services exposure (fertilisers partially offset mining-cycle volatility), justifying modest uplift. EODHD post-demerger 0.36 unreliable (only ~14 months of trading history). Source: normalised_baseline.wacc_build.beta.
A27: Cost of debt (pre-tax) | B27: 0.06 | C27: % | D27: AUD investment-grade BBB-tier corporate spread ~170bps over 10-yr sovereign. IPL pre-demerger BBB+/Baa1; post-demerger DNL likely BBB given smaller scale and concentrated cyclical exposure. Source: normalised_baseline.wacc_build.cost_of_debt_pretax.
A28: Equity market value (E) | B28: 6802 | C28: AUD m | D28: 1,884m shares x AUD 3.61 share price (21 May 2026 reference). Used for E/V weight in WACC. Source: normalised_baseline.wacc_build.equity_market_value.
A29: Debt market value (D) | B29: 1810 | C29: AUD m | D29: Reported net debt at 30 Sep 2025. Used for D/V weight in WACC — market-value weights reflect what the market actually sees today (not the steady-state normalised figure). Source: normalised_baseline.wacc_build.debt_market_value.
A31: RATE / TERMINAL-STATE ADJUSTMENTS (Muddle Through)
A32: Risk-free-rate scenario delta | B32: 0 | C32: bps | D32: Muddle Through: direction=neutral, magnitude=small -> delta 0bps. Rationale: 'real rates settle ~1% in Muddle Through baseline and stay there — baseline anchor against which other scenarios compared'.
A33: ERP scenario delta | B33: 0 | C33: bps | D33: Muddle Through: driver not populated (neutral).
A34: Terminal-growth-rate delta | B34: 0 | C34: bps | D34: Muddle Through: direction=neutral, magnitude=small -> delta 0bps. Rationale: 'long-term mining-customer demand approximately GDP-adjacent'.
A35: Baseline terminal growth | B35: 0.025 | C35: % | D35: GDP-adjacent Australian long-run nominal trend. Demographic-adaptation considerations sit beyond explicit 5-year horizon (§9.7 of architecture spec). Source: normalised_baseline.terminal_growth.
A37: DCF ENGINE PARAMETERS
A38: Horizon (explicit years) | B38: 5 | C38: years | D38: Phase 3.5 smoke-test setting. Architecture spec §2 supports either 5 or 10; longer horizon reduces terminal-share dominance (currently 73.9% of EV — over the 70% §11.4.2/§15.2 reasonableness threshold).
A39: Discounting convention | B39: end-period | D39: Smoke-test convention. Production §11.4 will use mid-period.
A41: Note on driver translation: | D41: Direction x magnitude -> numeric delta per src/vcc_valuations/translator.py rule tables (VOLUME_DELTA_PCT, MARGIN_DELTA_PP, RATE_DELTA_BPS). neutral/small = 0; positive/moderate = +3.5% (vol) / +1.5pp (margin) / +75bps (rate); etc.

Sheet P&L Summary
A1: DNL P&L summary — historicals + Muddle Through 5-year forecast (AUD m)
A3: Period | B3: FY2024 (combined) | C3: FY2025 | D3: TTM Mar-2026 | F3: Y1 (FY27e) | G3: Y2 (FY28e) | H3: Y3 (FY29e) | I3: Y4 (FY30e) | J3: Y5 (FY31e) | K3: Notes
A4: REVENUE
A5: Revenue | B5: 5279 | C5: 3710.1 | D5: 3905.4 | F5: =Assumptions!$B$3*(1+Assumptions!$B$14+Assumptions!$B$15+Assumptions!$B$16) -> 3983.508 | G5: =F5*(1+Assumptions!$B$14+Assumptions!$B$15+Assumptions!$B$16) -> 4063.1782 | H5: =G5*(1+Assumptions!$B$14+Assumptions!$B$15+Assumptions!$B$16) -> 4144.4417 | I5: =H5*(1+Assumptions!$B$14+Assumptions!$B$15+Assumptions!$B$16) -> 4227.3306 | J5: =I5*(1+Assumptions!$B$14+Assumptions!$B$15+Assumptions!$B$16) -> 4311.8772 | K5: Year 1 = base x (1+g); compounded annually. g = baseline 2.0% + scenario deltas (Muddle: 0).
A6: Revenue growth y/y | C6: =C5/B5-1 -> -0.29719644 | D6: =D5/C5-1 -> 0.052640091 | F6: =F5/D5-1 -> 0.02 | G6: =G5/F5-1 -> 0.02 | H6: =H5/G5-1 -> 0.02 | I6: =I5/H5-1 -> 0.02 | J6: =J5/I5-1 -> 0.02
A8: OPERATING PROFIT
A9: Cost of revenue | C9: 2688.3 | D9: =D5-D11 -> 1683.1 | K9: FY25 reported COGS; TTM derived from gross-profit.
A11: Gross profit | C11: 1021.8 | D11: 2222.3 | K11: Reported. TTM gross profit per EODHD; FY25 per income statement.
A12: Depreciation & amortisation | C12: 284.1 | F12: =F5*Assumptions!$B$6 -> 290.79608 | G12: =G5*Assumptions!$B$6 -> 296.61201 | H12: =H5*Assumptions!$B$6 -> 302.54425 | I12: =I5*Assumptions!$B$6 -> 308.59513 | J12: =J5*Assumptions!$B$6 -> 314.76703 | K12: Forecast = D&A/rev assumption x revenue.
A13: Selling, general & admin | C13: 957.7 | K13: FY25 reported. Not separately forecast (margin held flat at normalised level).
A14: EBIT | C14: 344.2 | D14: =D5*D15 -> 438.57642 | F14: =F5*(Assumptions!$B$4+Assumptions!$B$19+Assumptions!$B$20-Assumptions!$B$21) -> 537.77358 | G14: =G5*(Assumptions!$B$4+Assumptions!$B$19+Assumptions!$B$20-Assumptions!$B$21) -> 548.52905 | H14: =H5*(Assumptions!$B$4+Assumptions!$B$19+Assumptions!$B$20-Assumptions!$B$21) -> 559.49963 | I14: =I5*(Assumptions!$B$4+Assumptions!$B$19+Assumptions!$B$20-Assumptions!$B$21) -> 570.68963 | J14: =J5*(Assumptions!$B$4+Assumptions!$B$19+Assumptions!$B$20-Assumptions!$B$21) -> 582.10342 | K14: Forecast = Revenue x (normalised margin + scenario margin deltas).
A15: EBIT margin (memo) | C15: =C14/C5 -> 0.09277378 | D15: 0.1123 | F15: =F14/F5 -> 0.135 | G15: =G14/G5 -> 0.135 | H15: =H14/H5 -> 0.135 | I15: =I14/I5 -> 0.135 | J15: =J14/J5 -> 0.135
A17: TAX & NOPAT
A18: Tax on EBIT (statutory) | F18: =F14*Assumptions!$B$7 -> 161.33207 | G18: =G14*Assumptions!$B$7 -> 164.55872 | H18: =H14*Assumptions!$B$7 -> 167.84989 | I18: =I14*Assumptions!$B$7 -> 171.20689 | J18: =J14*Assumptions!$B$7 -> 174.63103 | K18: Forecast = EBIT x statutory tax rate (30%).
A19: NOPAT | F19: =F14-F18 -> 376.44151 | G19: =G14-G18 -> 383.97034 | H19: =H14-H18 -> 391.64974 | I19: =I14-I18 -> 399.48274 | J19: =J14-J18 -> 407.47239 | K19: EBIT - tax. Feeds the DCF.

Sheet Balance Sheet
A1: DNL balance sheet summary at 30 Sep 2025 (AUD m)
A3: Line | B3: AUD m | C3: Notes
A4: ASSETS
A5: Cash and short-term investments | B5: 647.2 | C5: Cash 207.2 + ST investments 440.0.
A6: Net receivables | B6: 840.5
A7: Inventory | B7: 519.1
A8: Other current assets | B8: 115.9
A9: Total current assets | B9: =SUM(B5:B8) -> 2122.7 | C9: Cash + receivables + inventory + other current.
A10: Property, plant & equipment (net) | B10: 2365.6
A11: Goodwill | B11: 1778.5 | C11: Acquisition-related; dominated by US deals over past two decades.
A12: Intangible assets | B12: 847.7
A13: Long-term investments | B13: 457.7
A14: Other non-current assets | B14: 73.3
A15: Total non-current assets | B15: =SUM(B10:B14) -> 5522.8 | C15: PP&E + goodwill + intangibles + LT inv + other NCA.
A16: Total assets | B16: =B9+B15 -> 7645.5 | C16: Current + non-current.
A18: LIABILITIES & EQUITY
A19: Accounts payable | B19: 733.7
A20: Short-term debt | B20: 626.3
A21: Other current liabilities | B21: 231.3
A22: Total current liabilities | B22: =SUM(B19:B21) -> 1591.3
A23: Long-term debt | B23: 1238.9
A24: Capital lease obligations | B24: 211.5 | C24: Lease liabilities under AASB 16.
A25: Other long-term liabilities | B25: 18.2
A26: Total non-current liabilities | B26: =SUM(B23:B25) -> 1468.6
A27: Total liabilities | B27: =B22+B26 -> 3059.9 | C27: Current + non-current liabilities.
A28: Total equity (attributable to shareholders) | B28: 4431.1 | C28: Per reported balance sheet.
A29: Minority interests | B29: -1.1 | C29: Immaterial; rounded out.
A31: DEBT & LEVERAGE
A32: Gross debt | B32: =B20+B23+B24 -> 2076.7 | C32: Short-term + long-term + capital leases.
A33: less: cash and short-term investments | B33: =-B5 -> -647.2
A34: Net debt (reported) | B34: =B32+B33 -> 1429.5 | C34: Reconciles to derived_metrics.net_debt (1,809.8).
A35: Net debt (normalised steady-state) | B35: =Assumptions!$B$10 -> 1300 | C35: Override used in DCF. Mid-point of estimated AUD 1.2-1.4bn underlying leverage.
A36: Net debt / EBITDA (TTM) | B36: =B34/853.6 -> 1.674672 | C36: TTM EBITDA AUD 853.6m. Reported leverage 2.12x.
A37: Net debt / EBITDA (normalised, Y1 forecast) | B37: =B35/('P&L Summary'!F14*1.535) -> 1.5748366 | C37: Approximate: normalised net debt over Year-1 forecast EBITDA (EBIT x ~1.53 for D&A pickup).

Sheet WACC Build
A1: DNL WACC component build-up (Muddle Through, 24 May 2026)
A3: Component | B3: Value | C3: Units | D3: Source / formula
A4: COST OF EQUITY (CAPM)
A5: Risk-free rate (Rf) | B5: =Assumptions!$B$24 -> 0.043 | C5: % | D5: 10Y AUD govt bond yield (May 2026).
A6: Equity risk premium (ERP) | B6: =Assumptions!$B$25 -> 0.05 | C6: % | D6: Mature-Australia ERP (Damodaran-style).
A7: Beta | B7: =Assumptions!$B$26 -> 1.15 | C7: unitless | D7: Pre-demerger IPL 1.05-1.10; pure-play uplift to 1.15.
A8: Cost of equity (Re) | B8: =B5+B7*B6 -> 0.1005 | C8: % | D8: Re = Rf + Beta x ERP.
A10: COST OF DEBT (AFTER-TAX)
A11: Cost of debt, pre-tax (Rd) | B11: =Assumptions!$B$27 -> 0.06 | C11: % | D11: AUD BBB-tier spread ~170bps over 10Y sovereign.
A12: Tax rate | B12: =Assumptions!$B$7 -> 0.3 | C12: % | D12: Australian statutory rate (30%).
A13: Cost of debt, after-tax | B13: =B11*(1-B12) -> 0.042 | C13: % | D13: Rd_after_tax = Rd_pretax x (1 - tax).
A15: CAPITAL-STRUCTURE WEIGHTS (market value)
A16: Equity market value (E) | B16: =Assumptions!$B$28 -> 6802 | C16: AUD m | D16: 1,884m shares x AUD 3.61 (21 May 2026).
A17: Debt market value (D) | B17: =Assumptions!$B$29 -> 1810 | C17: AUD m | D17: Reported net debt — market sees this on the balance sheet today.
A18: Enterprise value (V = E + D) | B18: =B16+B17 -> 8612 | C18: AUD m
A19: Equity weight (E/V) | B19: =B16/B18 -> 0.78982815 | C19: %
A20: Debt weight (D/V) | B20: =B17/B18 -> 0.21017185 | C20: %
A22: WACC
A23: Baseline WACC | B23: =B19*B8+B20*B13 -> 0.088204947 | C23: % | D23: WACC = (E/V) x Re + (D/V) x Rd_after_tax.
A24: Scenario WACC adjustment | B24: =(Assumptions!$B$32+Assumptions!$B$33)/10000 -> 0 | C24: % | D24: Sum of rate-driver deltas (bps -> decimal). Muddle Through = 0.
A25: Applied WACC (Muddle Through) | B25: =B23+B24 -> 0.088204947 | C25: % | D25: Baseline WACC + scenario rate adjustments.

Sheet DCF Worksheet
A1: DNL DCF — Muddle Through (5-yr explicit + Gordon-growth terminal)
A3: Line | B3: Y1 (FY27e) | C3: Y2 (FY28e) | D3: Y3 (FY29e) | E3: Y4 (FY30e) | F3: Y5 (FY31e) | G3: Terminal | H3: Notes
A4: INPUTS (linked from P&L Summary)
A5: Revenue | B5: ='P&L Summary'!F5 -> 3983.508 | C5: ='P&L Summary'!G5 -> 4063.1782 | D5: ='P&L Summary'!H5 -> 4144.4417 | E5: ='P&L Summary'!I5 -> 4227.3306 | F5: ='P&L Summary'!J5 -> 4311.8772 | H5: From P&L Summary Y1-Y5.
A6: EBIT margin | B6: ='P&L Summary'!F15 -> 0.135 | C6: ='P&L Summary'!G15 -> 0.135 | D6: ='P&L Summary'!H15 -> 0.135 | E6: ='P&L Summary'!I15 -> 0.135 | F6: ='P&L Summary'!J15 -> 0.135
A7: EBIT | B7: ='P&L Summary'!F14 -> 537.77358 | C7: ='P&L Summary'!G14 -> 548.52905 | D7: ='P&L Summary'!H14 -> 559.49963 | E7: ='P&L Summary'!I14 -> 570.68963 | F7: ='P&L Summary'!J14 -> 582.10342
A9: FREE CASH FLOW BRIDGE
A10: Less: tax on EBIT | B10: =-B7*Assumptions!$B$7 -> -161.33207 | C10: =-C7*Assumptions!$B$7 -> -164.55872 | D10: =-D7*Assumptions!$B$7 -> -167.84989 | E10: =-E7*Assumptions!$B$7 -> -171.20689 | F10: =-F7*Assumptions!$B$7 -> -174.63103
A11: NOPAT | B11: =B7+B10 -> 376.44151 | C11: =C7+C10 -> 383.97034 | D11: =D7+D10 -> 391.64974 | E11: =E7+E10 -> 399.48274 | F11: =F7+F10 -> 407.47239
A12: Plus: D&A | B12: =B5*Assumptions!$B$6 -> 290.79608 | C12: =C5*Assumptions!$B$6 -> 296.61201 | D12: =D5*Assumptions!$B$6 -> 302.54425 | E12: =E5*Assumptions!$B$6 -> 308.59513 | F12: =F5*Assumptions!$B$6 -> 314.76703
A13: Less: capex | B13: =-B5*Assumptions!$B$5 -> -278.84556 | C13: =-C5*Assumptions!$B$5 -> -284.42247 | D13: =-D5*Assumptions!$B$5 -> -290.11092 | E13: =-E5*Assumptions!$B$5 -> -295.91314 | F13: =-F5*Assumptions!$B$5 -> -301.8314
A14: Less: change in working capital | B14: =-Assumptions!$B$8 -> 0 | C14: =-Assumptions!$B$8 -> 0 | D14: =-Assumptions!$B$8 -> 0 | E14: =-Assumptions!$B$8 -> 0 | F14: =-Assumptions!$B$8 -> 0
A15: Unlevered free cash flow (FCFF) | B15: =SUM(B11:B14) -> 388.39203 | C15: =SUM(C11:C14) -> 396.15987 | D15: =SUM(D11:D14) -> 404.08307 | E15: =SUM(E11:E14) -> 412.16473 | F15: =SUM(F11:F14) -> 420.40802 | H15: NOPAT + D&A - Capex - delta WC.
A17: DISCOUNTING
A18: WACC | B18: ='WACC Build'!$B$25 -> 0.088204947 | C18: ='WACC Build'!$B$25 -> 0.088204947 | D18: ='WACC Build'!$B$25 -> 0.088204947 | E18: ='WACC Build'!$B$25 -> 0.088204947 | F18: ='WACC Build'!$B$25 -> 0.088204947
A19: Period (end-period convention) | B19: 1 | C19: 2 | D19: 3 | E19: 4 | F19: 5
A20: Discount factor | B20: =1/(1+B18)^B19 -> 0.91894455 | C20: =1/(1+C18)^C19 -> 0.84445908 | D20: =1/(1+D18)^D19 -> 0.77601106 | E20: =1/(1+E18)^E19 -> 0.71311113 | F20: =1/(1+F18)^F19 -> 0.65530959
A21: PV of FCFF | B21: =B15*B20 -> 356.91074 | C21: =C15*C20 -> 334.5408 | D21: =D15*D20 -> 313.57293 | E21: =E15*E20 -> 293.91926 | F21: =F15*F20 -> 275.49741
A23: TERMINAL VALUE (Gordon growth)
A24: Terminal growth rate (g) | G24: =Assumptions!$B$35+Assumptions!$B$34/10000 -> 0.025 | H24: Baseline terminal growth + scenario delta (Muddle: 0bps).
A25: Terminal-year FCF (= Y5 FCF x (1+g)) | G25: =F15*(1+G24) -> 430.91822
A26: Terminal value (= TFCF / (WACC - g)) | G26: =G25/(F18-G24) -> 6817.7927
A27: Discount factor at end Y5 | G27: =F20 -> 0.65530959
A28: PV of terminal value | G28: =G26*G27 -> 4467.7649
A30: VALUATION SUMMARY
A31: Sum of PV of explicit FCFF (Y1-Y5) | G31: =SUM(B21:F21) -> 1574.4411
A32: Plus: PV of terminal value | G32: =G28 -> 4467.7649
A33: Enterprise value (EV) | G33: =G31+G32 -> 6042.2061
A34: Less: net debt (steady-state normalised) | G34: =-Assumptions!$B$10 -> -1300
A35: Equity value | G35: =G33+G34 -> 4742.2061
A36: Shares outstanding | G36: =Assumptions!$B$11 -> 1875.91
A37: VALUE PER SHARE | G37: =G35/G36 -> 2.5279497
A39: DIAGNOSTICS
A40: Terminal share of EV | G40: =G32/G33 -> 0.73942611 | H40: Validator (§11.4.2 / §15.2): warn if > 70%. Production Step 7 to add fade-period to discipline this.
A41: Market reference per share | G41: 3.61 | H41: ASX close 21 May 2026; consensus target also AUD 3.61.
A42: Discount vs market | G42: =G37/G41-1 -> -0.29973693 | H42: Negative = our valuation below market; positive = above. Muddle Through is the more-sceptical-than-market case by design.
