Workbook

Sheet Cover
B1: DNL Scenario Comparison v4 — full methodology (9 June 2026)
B3: v4 methodology applied:
B4: Base EBIT (Q1) | C4: AUD 480m (corporate already in segment guidance per slides 27-28)
B5: Margin glide (Q2/Q3) | C5: +60 / +180 / +200 bps Y1-Y3 cum (reconciled to exit run rate AUD 495-525m)
B6: Gas roll-off overlay | C6: 0 / 0 / -50 / -100 / -150 bps Y1-Y5 cum (methodology section 3.2.1)
B7: Tax glide (section 3.6) | C7: Effective 22.5% (Y1) -> blended statutory 27.5% (Y5/terminal), linear
B8: WACC | C8: Single 8.28% across all scenarios (section 3.5). World-index beta 0.95 (section ii). Hamada with blended statutory tax shield (consistency)
B9: Company position (section 3.3) | C9: Five Forces spine: rivalry/competitive position -30bps + rivalry/product mix -10bps + new entrants/DNEL +15bps = -25bps net
B10: Equity bridge (Q7) | C10: Full Fertilisers separation map (slide 29): IPF Distribution / Geelong / Gibson Island / Perdaman / Phosphate Hill ARO + contingent
B11: Period A walk (Q6/Q8) | C11: OCF AUD 500m underlying (was AUD 290m); no buyback adjustment
B13: Headline result: | C13: Muddle Through AUD 3.59/share (-0.5% vs market AUD 3.61) -- central case essentially at market
B14: Framework discriminating power: | C14: Now lives in scenario asymmetry around Muddle Through, not in central-case disagreement
B16: Tabs:
B17: Inputs | C17: Scenario macro + scenario-conditional deltas + Five Forces decomposition
B18: WACC | C18: Single component build (constant across scenarios)
B19: DCF Outputs | C19: EV / equity / per share / terminal share
B20: Asymmetry | C20: Per-share vs Muddle Through; downside/upside ratio
B21: Scenario Rationale | C21: One-paragraph per scenario
B23: Methodology cross-references:
B24: Equity bridge & valuation mechanics | C24: design/methodology/equity_bridge_and_valuation_mechanics.md
B25: Architecture spec | C25: design/architecture.md v0.4
B26: DNL worked example | C26: analyses/dnl/valuations/dnl_muddle_through_valuation_v4_5forces.xlsx
B28: Constants:
B29: Applied WACC | C29: 8.28%
B30: Blended statutory tax | C30: 27.5%
B31: DNL company-position offset (net) | C31: -0.25%
B32: Market reference (21 May 2026) | C32: Share price AUD 3.61, consensus target AUD 3.61

Sheet Inputs
A1: Scenario inputs — v4 with Five Forces decomposition
A3: Input | B3: Muddle Through | C3: Orderly Convergence | D3: AI Prod. Lag | E3: Fragmen- tation | F3: Disorderly Climate | G3: Stagflation Persists
A5: SCENARIO MACRO BASELINE
A6: DM real GDP | B6: 0.02 | C6: 0.025 | D6: 0.017 | E6: 0.01 | F6: 0.015 | G6: 0.005
A7: DM inflation | B7: 0.025 | C7: 0.02 | D7: 0.025 | E7: 0.035 | F7: 0.035 | G7: 0.045
A8: Global mining real growth | B8: 0.025 | C8: 0.04 | D8: 0.02 | E8: 0.015 | F8: 0.02 | G8: 0
A9: Gas price growth | B9: 0.02 | C9: 0.015 | D9: 0.02 | E9: 0.04 | F9: 0.06 | G9: 0.05
A11: SCENARIO-CONDITIONAL DELTAS
A12: Margin delta (pp; gross/SG&A/input-cost net) | B12: 0 | C12: 0.005 | D12: 0.005 | E12: -0.03 | F12: -0.03 | G12: -0.075
A13: Terminal growth delta (bps) | B13: 0 | C13: 25 | D13: -25 | E13: -25 | F13: -75 | G13: -25
A14: Capex delta (climate scenario; pp) | B14: 0 | C14: 0 | D14: 0 | E14: 0 | F14: 0.03 | G14: 0
A16: DNL COMPANY POSITION (Five Forces; section 3.3) — same all scenarios
A17: Buyer power | B17: industry: HIGH (binding) | DNL: at average | mechanism: same mining-major customer mix as Orica | Δ: 0
A18: Supplier power | B18: industry: MODERATE | DNL: LOWER (favourable) | US gas contracts through 2028 | captured via gas roll-off overlay
A19: New entrants | B19: industry: LOW | DNL: LOWER in EM (favourable) | DNEL ramp LATAM/Africa | Δ: +15bps growth
A20: Substitutes | B20: industry: LOW | DNL: at average | intra-industry tech sub affects all players | Δ: 0
A21: Rivalry: competitive position | B21: industry: MODERATE | DNL: HIGHER (unfavourable) | #2 vs Orica #1 scale + tech lead | Δ: -30bps growth
A22: Rivalry: product-mix | B22: more bulk-ANFO weighted; less electronic detonator exposure | Δ: -10bps growth
A23: NET DNL company-position offset | B23: -25bps (= -30 + -10 + 15 + 0 + 0 + 0)
A25: DERIVED FROM CHAIN (per methodology section 2)
A26: DNL nominal revenue growth (applied) | B26: 0.061548876 | C26: 0.07441525 | D26: 0.055457585 | E26: 0.063040831 | F26: 0.075555975 | G26: 0.05487718
A27: Year 5 EBIT margin (with gas roll-off) | B27: 0.146 | C27: 0.151 | D27: 0.151 | E27: 0.116 | F27: 0.116 | G27: 0.071

Sheet WACC
A1: WACC — single build applied to all scenarios (methodology section 3.5)
A3: Component | B3: Value | C3: Notes
A4: Risk-free rate (Rf) | B4: 0.043 | C4: 10Y on-the-run CGS YTM (May 2026)
A5: Equity risk premium (ERP) | B5: 0.05 | C5: Mature-Australia
A6: Beta (world-index, Hamada re-levered) | B6: 0.95 | C6: World-index basis per WACC convention (ii)
A7: Cost of equity (CAPM) | B7: =B4+B6*B5 | C7: Re = Rf + Beta x ERP
A8: Cost of debt, pre-tax | B8: 0.06 | C8: BBB spread ~170bps
A9: Tax rate (blended statutory; consistency) | B9: 0.275 | C9: Single rate principle (section 3.6)
A10: Cost of debt, after-tax | B10: =B8*(1-B9)
A11: Equity market value (E) | B11: 6390
A12: Debt market value (D) | B12: 1260.8
A13: E/V | B13: =B11/(B11+B12)
A14: D/V | B14: =B12/(B11+B12)
A15: Applied WACC | B15: =B13*B7+B14*B10 | C15: Constant across scenarios; per methodology 3.5

Sheet DCF Outputs
A1: DCF outputs — v4 across all scenarios
A3: Output | B3: Muddle Through | C3: Orderly Convergence | D3: AI Prod. Lag | E3: Fragmen- tation | F3: Disorderly Climate | G3: Stagflation Persists
A5: DRIVERS (year 5)
A6: Revenue Y5 (AUD m) | B6: 4583.3064 | C6: 4867.8786 | D6: 4453.3091 | E6: 4615.6051 | F6: 4893.7751 | G6: 4441.078
A7: EBIT margin Y5 | B7: 0.146 | C7: 0.151 | D7: 0.151 | E7: 0.116 | F7: 0.116 | G7: 0.071
A8: EBIT Y5 (AUD m) | B8: 669.16273 | C8: 735.04967 | D8: 672.44968 | E8: 535.41019 | F8: 567.67791 | G8: 315.31654
A9: FCFF Y5 (AUD m) | B9: 498.8929 | C9: 547.51464 | D9: 500.88594 | E9: 402.01921 | F9: 279.43456 | G9: 241.92773
A11: DISCOUNTING
A12: Applied WACC (constant) | B12: 0.082754718 | C12: 0.082754718 | D12: 0.082754718 | E12: 0.082754718 | F12: 0.082754718 | G12: 0.082754718
A13: Applied terminal growth | B13: 0.025 | C13: 0.0275 | D13: 0.0225 | E13: 0.0225 | F13: 0.0175 | G13: 0.0225
A15: VALUATION
A16: Enterprise value | B16: 7736.6069 | C16: 8738.5112 | D16: 7538.5768 | E16: 6022.405 | F16: 3922.8855 | G16: 3634.9951
A17: Terminal share of EV | B17: 0.74786413 | C17: 0.7613779 | D17: 0.73680278 | E17: 0.74025033 | F17: 0.72581592 | G17: 0.73804625
A18: Net debt at val date (ex-leases) | B18: -1224.0329 | C18: -1224.0329 | D18: -1224.0329 | E18: -1224.0329 | F18: -1224.0329 | G18: -1224.0329
A19: Equity bridge (net) | B19: -151.65 | C19: -151.65 | D19: -151.65 | E19: -151.65 | F19: -151.65 | G19: -151.65
A20: Less: AASB 16 lease liabilities (H1 val date) | B20: -194.3 | C20: -194.3 | D20: -194.3 | E20: -194.3 | F20: -194.3 | G20: -194.3
A21: Equity value | B21: =B16+B18+B19+B20 | C21: =C16+C18+C19+C20 | D21: =D16+D18+D19+D20 | E21: =E16+E18+E19+E20 | F21: =F16+F18+F19+F20 | G21: =G16+G18+G19+G20
A22: PER SHARE
A23: Value per share | B23: =B21/1770 | C23: =C21/1770 | D23: =D21/1770 | E23: =E21/1770 | F23: =F21/1770 | G23: =G21/1770
A24: vs market AUD 3.61 | B24: =B23/3.61-1 | C24: =C23/3.61-1 | D24: =D23/3.61-1 | E24: =E23/3.61-1 | F24: =F23/3.61-1 | G24: =G23/3.61-1
A25: vs Muddle Through | B25: =B23/$B$23-1 | C25: =C23/$B$23-1 | D25: =D23/$B$23-1 | E25: =E23/$B$23-1 | F25: =F23/$B$23-1 | G25: =G23/$B$23-1
A27: Shares (m): 1770 (H1 FY26 anchor). Lease line added per Approach A (AASB 16 leases = debt).

Sheet Asymmetry
A1: Per-share asymmetry around Muddle Through
B3: Muddle Through | C3: Orderly Convergence | D3: AI Prod. Lag | E3: Fragmen- tation | F3: Disorderly Climate | G3: Stagflation Persists
A5: PER-SHARE COMPARISON
A6: Value per share | B6: ='DCF Outputs'!B23 | C6: ='DCF Outputs'!C23 | D6: ='DCF Outputs'!D23 | E6: ='DCF Outputs'!E23 | F6: ='DCF Outputs'!F23 | G6: ='DCF Outputs'!G23
A7: Δ vs Muddle Through (AUD) | B7: 0 | C7: 0.56604768 | D7: -0.1118814 | E7: -0.9684756 | F7: -2.1546448 | G7: -2.3172947
A8: Δ vs Muddle Through (%) | B8: 0 | C8: 0.15750925 | D8: -0.031132281 | E8: -0.26948944 | F8: -0.59955462 | G8: -0.64481382
A10: ASYMMETRY METRICS
A11: Upside (Orderly - MT) | B11: 0.56604768
A12: Worst downside (MT - Stagflation) | B12: 2.3172947
A13: Downside / upside ratio | B13: 4.0938155
A14: Negative asymmetry preserved: downside compression > upside lift. Central case essentially at market; framework discriminating power lives in this asymmetry rather than in central-case disagreement.

Sheet Scenario Rationale
A1: Scenario rationale
A3: Scenario | B3: Rationale
A4: Muddle Through (Interior, most-likely) | B4: Mining-customer capex cycle continues at current pace.
A5: Orderly Convergence (Upside boundary) | B5: Productivity acceleration + ordered geopolitics.
A6: AI Productivity Lag (Technology-downside boundary) | B6: AI fails to deliver economy-wide TFP.
A7: Fragmentation (Geopolitical-downside boundary) | B7: Trade fragmentation + resource nationalism.
A8: Disorderly Climate (Climate-downside boundary) | B8: Disorderly climate: carbon costs accelerate, capex demands.
A9: Stagflation Persists (Macro-downside boundary) | B9: Persistent stagflation: weak growth, high inflation, high gas costs.
